Workbook

Sheet Cover
B2: BILL OF QUANTITIES
B4: ELECTRICAL POWER DISTRIBUTION WORKS — DEWA AUTHORITY
B7: Project | C7: Proposed B+G+8+R Commercial & Residential Building
B8: Owner / Client | C8: Qutaiba Ameen Abdal Kija
B9: Plot No. | C9: 6731315 — Al Barsha South Third, Dubai, UAE
B10: MEP Consultant | C10: Future Art Engineering Consultancy
B11: Authority | C11: DEWA (Dubai Electricity & Water Authority)
B13: TENDER DETAILS
B14: Job No. | C14: FA_P379 / CRs B/010/25
B15: Drawing Ref | C15: P-001 … P-300 (14 sheets, Power)
B16: Drawing Date | C16: 19/06/2026
B17: BOQ Date | C17: 19/06/2026
B18: Addendum No. | C18: 0
B19: BOQ Status | C19: PRICED (INDICATIVE) — Dubai 2026 rates · POWER scope · review before submission
B20: Currency | C20: AED (UAE Dirham)
B21: VAT Rate | C21: 5% (UAE Federal)
B23: CONTRACTOR DETAILS
B24: Contractor | C24: SABI Engineering & Contracting LLC
B25: Address | C25: Dubai, United Arab Emirates
B26: Phone | C26: +971 4 XXX XXXX
B27: Email | C27: estimation@sabi.ae
B28: TRN | C28: 100XXXXXXXXXXXXX
B30: LIST OF BILLS
B31: Bill | C31: Description | H31: Sheet
B32: 1 | C32: General Items / Preliminaries | H32: Bill 1
B33: 2 | C33: HV / LV Main Distribution (Transformer, MDB, Generator, ATS, Capacitors) | H33: Bill 2
B34: 3 | C34: Sub-Main Distribution Boards (SMDBs) | H34: Bill 3
B35: 4 | C35: Distribution Boards (DBs) & Consumer Units | H35: Bill 4
B36: 5 | C36: LV Power Cables (Main + Distribution + Final Circuits) | H36: Bill 5
B37: 6 | C37: Cable Containment (Tray, Ladder, Trunking, Conduit) | H37: Bill 6
B38: 7 | C38: Wiring Devices & Accessories | H38: Bill 7
B39: 8 | C39: Lighting Fixtures (Internal + External) | H39: Bill 8
B40: 9 | C40: Earthing & Lightning Protection | H40: Bill 9
B41: 10 | C41: Emergency Lighting & Life Safety | H41: Bill 10
B42: 11 | C42: ELV Containment (Telephone, Data, CCTV, ACS, MATV, FA) | H42: Bill 11
B43: 12 | C43: Metering & Monitoring | H43: Bill 12
B44: 13 | C44: Testing, Commissioning & DEWA Approval | H44: Bill 13
B46: COMPLIANCE SUMMARY — what this BOQ already covers
B47: ✓ DEWA Distribution Standards · Dubai Municipality (DM) · Dubai Civil Defence (DCD) — see Preamble Sheet § 0 Statutory Compliance
B48: ✓ DEWA Smart Metering programme — Bill 12 (smart kWh meters single + three-phase, AMI-ready, MDM integration, Shams Dubai bi-directional, IEC 62052/62053)
B49: ✓ UAE Federal VAT (5 %) — line on Summary of Bills sheet, computed via Excel formula on the pre-VAT total
B50: ✓ Authority Fees & NOCs — Bill 1.5 (DEWA connection / load-letter / energising · RTA road permit · DM completion fee · DCD NOC fee)
B51: ✓ Central Battery System (CBS) — Bill 10.3 as alternative to self-contained luminaires; Fire Alarm / MEP integration — Bill 10.4 (shunt-trips, lift recall, dampers, mag-locks)
B52: ✓ All ~280 priceable line items pre-priced with INDICATIVE Dubai 2026 rates — review each line against actual supplier quotation before submission
B53: ✓ Origin / Brand column (H) pre-populated with Dubai AVL bands (Schneider/ABB/Siemens, Ducab/NCC, Itron/L+G, etc.) — overwrite with selected make at tender time
B54: ✓ Drawing references (column C) mapped to specific P-001 … P-300 sheet numbers per item type (SLD / floor plan / LV-room / cable-tray detail)
B55: ✓ Engineering corrections from PDF_vs_XLSX_Comparison.pdf applied: LVP-01 risers 150mm² · fire pump 185mm² FR · ESMDB-G 300mm² FR · building totals on Cover
B57: DATA PROVENANCE — measured from project drawings vs industry allowance
B58: 📐 MEASURED | C58: derived from project drawings (P-001 … P-300) via the AI extraction — quantities and counts are project-specific
B59: 📋 ALLOWANCE | C59: industry-standard template / fixture default — quantities are allowances based on building size, NOT counted from drawings — review before submission
B60: Bill | C60: Description | D60: Source | E60: Notes
B61: Bill 1 | C61: Preliminaries + Authority Fees | D61: 📋 ALLOWANCE | E61: Industry allowance (mob, insurance, submittals, DEWA/RTA/DM/DCD fees)
B62: Bill 2.1 | C62: HV side (transformer / RMU / room civil) | D62: 📋 ALLOWANCE | E62: Industry template — transformer kVA sized from MD only
B63: Bill 2.2 | C63: LV panels (LVP-01, LVP-02) | D63: 📐 MEASURED | E63: From P-200 SLD — ACB ratings, MCCB schedules, capacitor banks
B64: Bill 2.3 | C64: Generator + ATS | D64: 📐 MEASURED | E64: From P-200 SLD — kVA + ATS rating
B65: Bill 3 | C65: Sub-Main Distribution Boards (26) | D65: 📐 MEASURED | E65: From P-201 SLD — every SMDB tag, rating, floor, connected load
B66: Bill 4 | C66: Distribution Boards (107) | D66: 📐 MEASURED | E66: From P-103…P-108 floor plans + P-201 SLD — DB groups, counts
B67: Bill 5.1 | C67: XLPE LV→SMDB risers | D67: 📐 MEASURED | E67: From cable_schedule — every run, size, length per AI extraction
B68: Bill 5.2 | C68: Fire-Rated LV→SMDB | D68: 📐 MEASURED | E68: From cable_schedule — with engineering corrections applied
B69: Bill 5.3 | C69: XLPE SMDB→DB distribution | D69: 📐 MEASURED | E69: From smdb_to_db_cables / cable_schedule (non-LV-source filter)
B70: Bill 5.4 | C70: FR SMDB→DB distribution | D70: 📐 MEASURED | E70: From smdb_to_db_cables / cable_schedule
B71: Bill 5.5 | C71: LSZH escape-route final circuits | D71: 📋 ALLOWANCE | E71: Industry allowance — quantities by floor count × typical loop
... B84: Bill 13 | C84: Testing, Commissioning & Authority | D84: 📋 ALLOWANCE | E84: Industry allowance — IR / continuity / ELI / RCD + DEWA + DM + DCD
B86: STATUS: PRICED (INDICATIVE) — Dubai 2026 rates · POWER scope · review before submission

Sheet Preamble & Standards
B2: PREAMBLE & APPLICABLE STANDARDS
B4: 0. STATUTORY COMPLIANCE — UAE / DUBAI AUTHORITIES
B5: The works under this BOQ shall fully comply with the requirements of the following Dubai and UAE authorities. The contractor shall obtain all approvals, attend witnessed inspections, and submit all documentation required by each authority as part of the contract.
B6: Authority | C6: Scope of compliance
B7: DEWA | C7: Dubai Electricity & Water Authority — Distribution Standards, Service Connection Specifications, Smart Grid / Smart Metering programme, witnessed inspections, energising, meter sealing, As-Built filing.
B8: Dubai Municipality | C8: Building Code, Local Order 89/1994 (Building Regulations) and amendments, electrical safety inspections, occupancy / completion certificate clearance.
B9: DCD | C9: Dubai Civil Defence — UAE Fire & Life Safety Code of Practice (latest edition); fire-rated containment, FR/LSZH cable selection, emergency lighting, fire-fighter's lift, smoke-control fan power supplies.
B10: UAE Federal | C10: Federal Tax Authority — VAT (5%) per UAE VAT Law (Federal Decree-Law No. 8 of 2017); MoCCAE / ESMA conformity certificates for electrical equipment placed on UAE market.
B12: 1. SCOPE OF WORKS
B13: Supply, installation, testing and commissioning of the complete LV electrical distribution system, lighting, small power, earthing & lightning protection, metering and life-safety related electrical installations for the project, in accordance with the tender drawings, specifications, applicable standards, and authority requirements (DEWA, Dubai Municipality, Dubai Civil Defence). The scope shall include all materials, labour, plant, supervision, transport, scaffolding, builder's work in connection, testing instruments, commissioning, As-Built drawings and O&M manuals.
B15: 2. APPLICABLE STANDARDS
B16: Standard | C16: Description
B17: DEWA | C17: Distribution Standards & Authority Regulations (latest edition)
B18: DEWA Smart Grid | C18: Smart Metering Programme / AMI Specifications / Shams Dubai
B19: DM | C19: Dubai Municipality Building Code & Electrical Inspection Standards
B20: DM Local Order | C20: Local Order 89/1994 — Building Regulations and amendments
B21: DCD | C21: Dubai Civil Defence — UAE Fire & Life Safety Code of Practice (latest)
B22: BS 7671 | C22: IEE Wiring Regulations (18th Edition / latest)
B23: IEC 60364 | C23: Low-voltage electrical installations
B24: IEC 60439 | C24: LV switchgear and controlgear assemblies (Form separation)
B25: IEC 60947 | C25: LV switchgear (ACBs, MCCBs, contactors)
B26: IEC 60331 | C26: Fire-resisting characteristics of electric cables
B27: BS 6387 CWZ | C27: Performance requirements for fire-rated cables
... B35: UAE FTA | C35: Federal Tax Authority — VAT (5%) on tender total per Federal Decree-Law 8/2017
B37: 3. ABBREVIATIONS
B38: Abbr. | C38: Meaning
B39: ACB | C39: Air Circuit Breaker
B40: MCCB | C40: Moulded Case Circuit Breaker
B41: MCB | C41: Miniature Circuit Breaker
B42: RCD | C42: Residual Current Device
B43: LVP | C43: LV Panel (Main)
B44: SMDB | C44: Sub-Main Distribution Board
B45: ESMDB | C45: Emergency SMDB
B46: DB | C46: Distribution Board
B47: EDB | C47: Emergency DB
B48: ATS | C48: Automatic Transfer Switch
B49: XLPE | C49: Cross-Linked Polyethylene
... B64: IP55/IP65 | C64: Ingress Protection ratings
B67: 4. PRICING NOTES
B68: (1) | C68: All rates shall include supply, delivery, off-loading, storage, installation, fixings, support steelwork, painting, identification labelling, testing, commissioning, and handover.
B69: (2) | C69: All quantities are estimated from tender drawings; the contractor shall verify on site before procurement. No claim for variation will be entertained for take-off discrepancies within ±5% of the BOQ quantity.
B70: (3) | C70: Cable lengths include +10% installation allowance (vertical rise + horizontal route + termination + slack).
B71: (4) | C71: Where a "lot" or "item" unit is used, the rate shall cover the complete scope described in that item including all incidentals.
B72: (5) | C72: Provisional sums (PS) are net rates; the contractor shall add a percentage for overheads, profit, and attendance separately at the foot of each Bill where applicable.
B73: (6) | C73: All prices shall be in UAE Dirhams (AED), exclusive of VAT. VAT at 5% will be added at the foot of the Summary in accordance with UAE Federal Tax Authority requirements.
B74: (7) | C74: Rates shall remain firm and fixed for the duration of the contract including the Defects Liability Period unless otherwise agreed in writing.

Sheet Bill 1 - Preliminaries
A1: BILL No. 1 — GENERAL ITEMS / PRELIMINARIES
A2: Project: Proposed B+G+8+R Commercial & Residential Building, Plot 6731315, Al Barsha South Third, Dubai, UAE | Job: FA_P379 / CRs B/010/25 | Authority: DEWA (Dubai Electricity & Water Authority)
A3: Item | B3: Description | C3: Reference | D3: Unit | E3: Qty | F3: Rate (AED) | G3: Amount (AED) | H3: Origin / Brand
A4: 1.1 — PROJECT MOBILISATION & SITE ESTABLISHMENT
A5: 1.1.1 | B5: Mobilisation to site, including transport of plant, tools, materials and personnel. | C5: — | D5: Sum | E5: 1 | F5: 125000 | G5: =IF(OR(E5="",F5=""),"",E5*F5) | H5: 📋 — (contractor selection)
A6: 1.1.2 | B6: Site offices, storage compounds, sanitary and welfare facilities for the duration of the works. | C6: — | D6: Sum | E6: 1 | F6: 85000 | G6: =IF(OR(E6="",F6=""),"",E6*F6) | H6: 📋 — (contractor selection)
A7: 1.1.3 | B7: Site hoarding, fencing and security as per main contractor / consultant requirements. | C7: — | D7: Sum | E7: 1 | F7: 35000 | G7: =IF(OR(E7="",F7=""),"",E7*F7) | H7: 📋 — (contractor selection)
A8: 1.1.4 | B8: Health & Safety plan, PPE, fall-arrest and electrical safety (LOTO) provisions for the duration. | C8: — | D8: Sum | E8: 1 | F8: 18000 | G8: =IF(OR(E8="",F8=""),"",E8*F8) | H8: 📋 — (contractor selection)
A9: 1.1.5 | B9: Coordination with main contractor and other MEP trades — shop-drawing review meetings, BIM coordination as required. | C9: — | D9: Sum | E9: 1 | F9: 25000 | G9: =IF(OR(E9="",F9=""),"",E9*F9) | H9: 📋 — (contractor selection)
A10: Sub-Total 1.1 | G10: =SUM(G5:G10)
A12: 1.2 — INSURANCE & BONDS
A13: 1.2.1 | B13: Contractor's All Risks (CAR) insurance for the contract value, full duration plus DLP. | C13: — | D13: Sum | E13: 1 | F13: 85000 | G13: =IF(OR(E13="",F13=""),"",E13*F13) | H13: 📋 — (contractor selection)
A14: 1.2.2 | B14: Workmen's Compensation and Public Liability insurance. | C14: — | D14: Sum | E14: 1 | F14: 45000 | G14: =IF(OR(E14="",F14=""),"",E14*F14) | H14: 📋 — (contractor selection)
A15: 1.2.3 | B15: Performance bond (10% of contract value) — bank guarantee in favour of the employer. | C15: — | D15: Sum | E15: 1 | F15: 18000 | G15: =IF(OR(E15="",F15=""),"",E15*F15) | H15: 📋 — (contractor selection)
A16: 1.2.4 | B16: Advance payment guarantee — bank guarantee against advance. | C16: — | D16: Sum | E16: 1 | F16: 12000 | G16: =IF(OR(E16="",F16=""),"",E16*F16) | H16: 📋 — (contractor selection)
A17: Sub-Total 1.2 | G17: =SUM(G13:G17)
A19: 1.3 — TEMPORARY UTILITIES & TESTING INSTRUMENTS
A20: 1.3.1 | B20: Temporary power supply during construction — generator, distribution, metering, fuel. | C20: — | D20: Sum | E20: 1 | F20: 85000 | G20: =IF(OR(E20="",F20=""),"",E20*F20) | H20: 📋 — (contractor selection)
A21: 1.3.2 | B21: Temporary lighting in areas of work as required for safe execution. | C21: — | D21: Sum | E21: 1 | F21: 25000 | G21: =IF(OR(E21="",F21=""),"",E21*F21) | H21: 📋 — (contractor selection)
A22: 1.3.3 | B22: Provision of all testing instruments — Megger 500V/1000V, earth tester, multimeter, RCD tester, loop tester, calibration certificates current. | C22: — | D22: Sum | E22: 1 | F22: 5500 | G22: =IF(OR(E22="",F22=""),"",E22*F22) | H22: 📋 — (contractor selection)
A23: Sub-Total 1.3 | G23: =SUM(G20:G23)
A25: 1.4 — SUBMITTALS, AS-BUILTS, O&M MANUALS
A26: 1.4.1 | B26: Shop drawings (AutoCAD) — full set, multiple revisions until approved. | C26: — | D26: Sum | E26: 1 | F26: 85000 | G26: =IF(OR(E26="",F26=""),"",E26*F26) | H26: 📋 — (contractor selection)
A27: 1.4.2 | B27: Material approval submittals — datasheets, samples, manufacturer's certificates, country-of-origin declarations. | C27: — | D27: Sum | E27: 1 | F27: 35000 | G27: =IF(OR(E27="",F27=""),"",E27*F27) | H27: 📋 — (contractor selection)
A28: 1.4.3 | B28: As-Built drawings (AutoCAD + PDF, 4 hard copies) at handover. | C28: — | D28: Sum | E28: 1 | F28: 45000 | G28: =IF(OR(E28="",F28=""),"",E28*F28) | H28: 📋 — (contractor selection)
A29: 1.4.4 | B29: Operation & Maintenance manuals (4 hard copies + PDF) at handover, including spare-parts list. | C29: — | D29: Sum | E29: 1 | F29: 38000 | G29: =IF(OR(E29="",F29=""),"",E29*F29) | H29: 📋 — (contractor selection)
A30: 1.4.5 | B30: Defects Liability Period support (12 months from handover) — site attendance, replacement of defective materials, retesting. | C30: — | D30: Sum | E30: 1 | F30: 12000 | G30: =IF(OR(E30="",F30=""),"",E30*F30) | H30: 📋 — (contractor selection)
A31: Sub-Total 1.4 | G31: =SUM(G26:G31)
A33: 1.5 — AUTHORITY FEES, NOCs & PERMITS
A34: 1.5.1 | B34: DEWA HV/LV connection capacity charges (per kVA, DEWA tariff). Provisional sum — final amount per DEWA load-letter response. | C34: DEWA / DM / DCD / RTA tariff | D34: Sum | E34: 1 | F34: 350000 | G34: =IF(OR(E34="",F34=""),"",E34*F34) | H34: 📋 DEWA / DM / DCD / RTA
A35: 1.5.2 | B35: DEWA load-letter application & approval fees (capacity allocation, RMU/substation siting, voltage level confirmation). | C35: DEWA / DM / DCD / RTA tariff | D35: Sum | E35: 1 | F35: 8000 | G35: =IF(OR(E35="",F35=""),"",E35*F35) | H35: 📋 DEWA / DM / DCD / RTA
A36: 1.5.3 | B36: DEWA energising application fee — submission, processing, witness arrangement, meter sealing. | C36: DEWA / DM / DCD / RTA tariff | D36: Sum | E36: 1 | F36: 12000 | G36: =IF(OR(E36="",F36=""),"",E36*F36) | H36: 📋 DEWA / DM / DCD / RTA
A37: 1.5.4 | B37: RTA road-cutting permit + reinstatement (where HV/LV cabling crosses public road or pavement). Provisional sum. | C37: DEWA / DM / DCD / RTA tariff | D37: Sum | E37: 1 | F37: 45000 | G37: =IF(OR(E37="",F37=""),"",E37*F37) | H37: 📋 DEWA / DM / DCD / RTA
A38: 1.5.5 | B38: Dubai Municipality (DM) electrical inspection & completion-certificate fee — for occupancy / completion sign-off. | C38: DEWA / DM / DCD / RTA tariff | D38: Sum | E38: 1 | F38: 18000 | G38: =IF(OR(E38="",F38=""),"",E38*F38) | H38: 📋 DEWA / DM / DCD / RTA
A39: 1.5.6 | B39: Dubai Civil Defence (DCD) electrical clearance NOC fee — life-safety clearance for fire pump, smoke control, emergency lighting. | C39: DEWA / DM / DCD / RTA tariff | D39: Sum | E39: 1 | F39: 12000 | G39: =IF(OR(E39="",F39=""),"",E39*F39) | H39: 📋 DEWA / DM / DCD / RTA
A40: Sub-Total 1.5 | G40: =SUM(G34:G40)
A43: BILL 1 — TOTAL CARRIED TO SUMMARY | G43: =SUMIF(G4:G41,"<>")

Sheet Bill 2 - HV-LV Main
A1: BILL No. 2 — HV / LV MAIN DISTRIBUTION
A2: Project: Proposed B+G+8+R Commercial & Residential Building, Plot 6731315, Al Barsha South Third, Dubai, UAE | Job: FA_P379 / CRs B/010/25 | Authority: DEWA (Dubai Electricity & Water Authority)
A3: Item | B3: Description | C3: Reference | D3: Unit | E3: Qty | F3: Rate (AED) | G3: Amount (AED) | H3: Origin / Brand
A4: 2.1 — HV INCOMING SUPPLY & TRANSFORMER (DEWA-coordinated)
A5: 2.1.1 | B5: DEWA HV incoming service connection (RMU / package substation, supplied & installed by DEWA). Contractor allowance for coordination, application, attendance and acceptance. | C5: P-200 (SLD) / P-300 (LV room) | D5: Lot | E5: 1 | F5: 0 | G5: =IF(OR(E5="",F5=""),"",E5*F5) | H5: 📋 DEWA-listed
A6: 2.1.2 | B6: HV / LV distribution transformer — 2000 kVA, 11 kV / 0.4 kV, 50 Hz, vector group Dyn11, K-Factor rating ≥ K-13 (suitable for non-linear loads — LED lighting, EV chargers, VFDs; uplift to K-20 if EV load > 20 % of MD), cast-resin (dry-type) construction with encapsulated F-class windings, IP31 enclosure, anti-vibration mounts, ±2.5 % / ±5 % off-circuit tap changer, oil-free, low-loss DEWA-listed manufacturer. Sized for Building MD ~? kW + 25 % spare. Includes installation, energising, witnessed routine test, commissioning report. | C6: P-200 (SLD) / P-300 (LV room) | D6: Nr | E6: 1 | F6: 240000 | G6: =IF(OR(E6="",F6=""),"",E6*F6) | H6: 📋 Schneider / ABB / Siemens / Trafo Union
A7: 2.1.3 | B7: 11 kV HV cable (single-core 3×1C, XLPE/CWS/PVC, copper screen) from RMU to transformer HV side — complete with stress cones, heat-shrink terminations, fire stopping at penetrations, earthing, ID phase markers. | C7: P-200 (SLD) / P-300 (LV room) | D7: m | E7: 30 | F7: 18000 | G7: =IF(OR(E7="",F7=""),"",E7*F7) | H7: 📋 — (contractor selection)
A8: 2.1.4 | B8: Transformer room civil / MEP coordination — pressure-relief vents, mechanical ventilation, drainage, fire-rated enclosure (≥ 2 h), DEWA-spec oil bund where oil-filled (N/A for cast-resin) — coordination only. | C8: P-200 (SLD) / P-300 (LV room) | D8: Sum | E8: 1 | F8: 35000 | G8: =IF(OR(E8="",F8=""),"",E8*F8) | H8: 📋 Schneider / ABB / Siemens / Trafo Union
A9: Sub-Total 2.1 | G9: =SUM(G5:G9)
A11: 2.2 — LV PANELS (Supply, Install, Test & Commission)
A12: 2.2.1 | B12: Main LV Panel — sized per Maximum Demand. Supply, install, test, commission complete with ACB, busbars, MCCBs as per SLD. | C12: P-200 (SLD) / P-300 (LV room) | D12: Nr | E12: 1 | G12: =IF(OR(E12="",F12=""),"",E12*F12) | H12: 📐 Coordinate with consultant
A13: Sub-Total 2.2 | G13: =SUM(G12:G13)
A15: 2.3 — STANDBY GENERATOR & ATS
A16: 2.3.1 | B16: Standby generator + ATS — sized per essential-load schedule. Supply, install, commission complete. | C16: P-200 (SLD) / P-300 (LV room) | D16: Set | E16: 1 | F16: 80000 | G16: =IF(OR(E16="",F16=""),"",E16*F16) | H16: 📐 Cummins / Caterpillar / FG Wilson / Perkins
A17: Sub-Total 2.3 | G17: =SUM(G16:G17)
A20: BILL 2 — TOTAL CARRIED TO SUMMARY | G20: =SUMIF(G4:G18,"<>")

Sheet Bill 3 - SMDBs
A1: BILL No. 3 — SUB-MAIN DISTRIBUTION BOARDS (SMDBS)
A2: Project: Proposed B+G+8+R Commercial & Residential Building, Plot 6731315, Al Barsha South Third, Dubai, UAE | Job: FA_P379 / CRs B/010/25 | Authority: DEWA (Dubai Electricity & Water Authority)
A3: Item | B3: Description | C3: Reference | D3: Unit | E3: Qty | F3: Rate (AED) | G3: Amount (AED) | H3: Origin / Brand
A4: 3.1 — TYPICAL FLOOR SMDBs (1F–8F)
A5: 3.1.1 | B5: SMDB-1F: floor-standing SMDB, IP31 powder-coated mild-steel enclosure with padlockable hinged door, 415 V / 3P+N+E, 300A TP MCCB ≥35 kA Icu incomer, busbar 300 A Cu electro-tin plated, Form 2b separation, neutral / earth bars, outgoing MCCBs / MCBs / RCBOs as per SLD, MEB sub-bar bonded to building MEB, ID-engraved circuit labels, padlockable hinged door, manufacturer's factory acceptance test (FAT) certificate. Fire-rated cable glands + LSZH gland-kits at all FR feeder terminations. Connected load 150.86 kW. Supply, install, terminate, energise, witnessed routine test. | C5: P-201 (SLD) / P-103 (1F) | D5: Nr | E5: 1 | F5: 32000 | G5: =IF(OR(E5="",F5=""),"",E5*F5) | H5: 📐 Schneider / Hager / Legrand / ABB
A6: 3.1.2 | B6: SMDB-2F: floor-standing SMDB, IP31 powder-coated mild-steel enclosure with padlockable hinged door, 415 V / 3P+N+E, 300A TP MCCB ≥35 kA Icu incomer, busbar 300 A Cu electro-tin plated, Form 2b separation, neutral / earth bars, outgoing MCCBs / MCBs / RCBOs as per SLD, MEB sub-bar bonded to building MEB, ID-engraved circuit labels, padlockable hinged door, manufacturer's factory acceptance test (FAT) certificate. Fire-rated cable glands + LSZH gland-kits at all FR feeder terminations. Connected load 150.86 kW. Supply, install, terminate, energise, witnessed routine test. | C6: P-201 (SLD) / P-104 (2F) | D6: Nr | E6: 1 | F6: 32000 | G6: =IF(OR(E6="",F6=""),"",E6*F6) | H6: 📐 Schneider / Hager / Legrand / ABB
A7: 3.1.3 | B7: SMDB-3F: floor-standing SMDB, IP31 powder-coated mild-steel enclosure with padlockable hinged door, 415 V / 3P+N+E, 300A TP MCCB ≥35 kA Icu incomer, busbar 300 A Cu electro-tin plated, Form 2b separation, neutral / earth bars, outgoing MCCBs / MCBs / RCBOs as per SLD, MEB sub-bar bonded to building MEB, ID-engraved circuit labels, padlockable hinged door, manufacturer's factory acceptance test (FAT) certificate. Fire-rated cable glands + LSZH gland-kits at all FR feeder terminations. Connected load 150.86 kW. Supply, install, terminate, energise, witnessed routine test. | C7: P-201 (SLD) / P-105 (3F) | D7: Nr | E7: 1 | F7: 32000 | G7: =IF(OR(E7="",F7=""),"",E7*F7) | H7: 📐 Schneider / Hager / Legrand / ABB
A8: 3.1.4 | B8: SMDB-4F: floor-standing SMDB, IP31 powder-coated mild-steel enclosure with padlockable hinged door, 415 V / 3P+N+E, 300A TP MCCB ≥35 kA Icu incomer, busbar 300 A Cu electro-tin plated, Form 2b separation, neutral / earth bars, outgoing MCCBs / MCBs / RCBOs as per SLD, MEB sub-bar bonded to building MEB, ID-engraved circuit labels, padlockable hinged door, manufacturer's factory acceptance test (FAT) certificate. Fire-rated cable glands + LSZH gland-kits at all FR feeder terminations. Connected load 150.86 kW. Supply, install, terminate, energise, witnessed routine test. | C8: P-201 (SLD) / P-104 (4F) | D8: Nr | E8: 1 | F8: 32000 | G8: =IF(OR(E8="",F8=""),"",E8*F8) | H8: 📐 Schneider / Hager / Legrand / ABB
A9: 3.1.5 | B9: SMDB-5F: floor-standing SMDB, IP31 powder-coated mild-steel enclosure with padlockable hinged door, 415 V / 3P+N+E, 300A TP MCCB ≥35 kA Icu incomer, busbar 300 A Cu electro-tin plated, Form 2b separation, neutral / earth bars, outgoing MCCBs / MCBs / RCBOs as per SLD, MEB sub-bar bonded to building MEB, ID-engraved circuit labels, padlockable hinged door, manufacturer's factory acceptance test (FAT) certificate. Fire-rated cable glands + LSZH gland-kits at all FR feeder terminations. Connected load 150.86 kW. Supply, install, terminate, energise, witnessed routine test. | C9: P-201 (SLD) / P-105 (5F) | D9: Nr | E9: 1 | F9: 32000 | G9: =IF(OR(E9="",F9=""),"",E9*F9) | H9: 📐 Schneider / Hager / Legrand / ABB
A10: 3.1.6 | B10: SMDB-6F: floor-standing SMDB, IP31 powder-coated mild-steel enclosure with padlockable hinged door, 415 V / 3P+N+E, 300A TP MCCB ≥35 kA Icu incomer, busbar 300 A Cu electro-tin plated, Form 2b separation, neutral / earth bars, outgoing MCCBs / MCBs / RCBOs as per SLD, MEB sub-bar bonded to building MEB, ID-engraved circuit labels, padlockable hinged door, manufacturer's factory acceptance test (FAT) certificate. Fire-rated cable glands + LSZH gland-kits at all FR feeder terminations. Connected load 150.86 kW. Supply, install, terminate, energise, witnessed routine test. | C10: P-201 (SLD) / P-104 (6F) | D10: Nr | E10: 1 | F10: 32000 | G10: =IF(OR(E10="",F10=""),"",E10*F10) | H10: 📐 Schneider / Hager / Legrand / ABB
A11: 3.1.7 | B11: SMDB-7F: floor-standing SMDB, IP31 powder-coated mild-steel enclosure with padlockable hinged door, 415 V / 3P+N+E, 300A TP MCCB ≥35 kA Icu incomer, busbar 300 A Cu electro-tin plated, Form 2b separation, neutral / earth bars, outgoing MCCBs / MCBs / RCBOs as per SLD, MEB sub-bar bonded to building MEB, ID-engraved circuit labels, padlockable hinged door, manufacturer's factory acceptance test (FAT) certificate. Fire-rated cable glands + LSZH gland-kits at all FR feeder terminations. Connected load 150.86 kW. Supply, install, terminate, energise, witnessed routine test. | C11: P-201 (SLD) / P-105 (7F) | D11: Nr | E11: 1 | F11: 32000 | G11: =IF(OR(E11="",F11=""),"",E11*F11) | H11: 📐 Schneider / Hager / Legrand / ABB
A12: 3.1.8 | B12: SMDB-8F: floor-standing SMDB, IP31 powder-coated mild-steel enclosure with padlockable hinged door, 415 V / 3P+N+E, 300A TP MCCB ≥35 kA Icu incomer, busbar 300 A Cu electro-tin plated, Form 2b separation, neutral / earth bars, outgoing MCCBs / MCBs / RCBOs as per SLD, MEB sub-bar bonded to building MEB, ID-engraved circuit labels, padlockable hinged door, manufacturer's factory acceptance test (FAT) certificate. Fire-rated cable glands + LSZH gland-kits at all FR feeder terminations. Connected load 150.86 kW. Supply, install, terminate, energise, witnessed routine test. | C12: P-201 (SLD) / P-104 (8F) | D12: Nr | E12: 1 | F12: 32000 | G12: =IF(OR(E12="",F12=""),"",E12*F12) | H12: 📐 Schneider / Hager / Legrand / ABB
A13: Sub-Total 3.1 | G13: =SUM(G5:G13)
A15: 3.2 — GROUND FLOOR SMDBs
A16: 3.2.1 | B16: SMDB-G: wall-mounted SMDB, IP31 powder-coated mild-steel enclosure with padlockable hinged door, 415 V / 3P+N+E, 125A TP MCCB ≥35 kA Icu incomer, busbar 125 A Cu electro-tin plated, Form 2b separation, neutral / earth bars, outgoing MCCBs / MCBs / RCBOs as per SLD, MEB sub-bar bonded to building MEB, ID-engraved circuit labels, padlockable hinged door, manufacturer's factory acceptance test (FAT) certificate. Fire-rated cable glands + LSZH gland-kits at all FR feeder terminations. Connected load 60.55 kW. Supply, install, terminate, energise, witnessed routine test. | C16: P-201 (SLD) / P-102 (Ground) | D16: Nr | E16: 1 | F16: 14000 | G16: =IF(OR(E16="",F16=""),"",E16*F16) | H16: 📐 Schneider / Hager / Legrand / ABB
A17: 3.2.2 | B17: SMDB-SH01: wall-mounted SMDB, IP31 powder-coated mild-steel enclosure with padlockable hinged door, 415 V / 3P+N+E, 40A TP MCCB ≥35 kA Icu incomer, busbar 40 A Cu electro-tin plated, Form 2b separation, neutral / earth bars, outgoing MCCBs / MCBs / RCBOs as per SLD, MEB sub-bar bonded to building MEB, ID-engraved circuit labels, padlockable hinged door, manufacturer's factory acceptance test (FAT) certificate. Fire-rated cable glands + LSZH gland-kits at all FR feeder terminations. Connected load 15 kW. Supply, install, terminate, energise, witnessed routine test. | C17: P-201 (SLD) | D17: Nr | E17: 1 | F17: 6000 | G17: =IF(OR(E17="",F17=""),"",E17*F17) | H17: 📐 Schneider / Hager / Legrand / ABB
A18: 3.2.3 | B18: SMDB-SH02: wall-mounted SMDB, IP31 powder-coated mild-steel enclosure with padlockable hinged door, 415 V / 3P+N+E, 40A TP MCCB ≥35 kA Icu incomer, busbar 40 A Cu electro-tin plated, Form 2b separation, neutral / earth bars, outgoing MCCBs / MCBs / RCBOs as per SLD, MEB sub-bar bonded to building MEB, ID-engraved circuit labels, padlockable hinged door, manufacturer's factory acceptance test (FAT) certificate. Fire-rated cable glands + LSZH gland-kits at all FR feeder terminations. Connected load 15 kW. Supply, install, terminate, energise, witnessed routine test. | C18: P-201 (SLD) | D18: Nr | E18: 1 | F18: 6000 | G18: =IF(OR(E18="",F18=""),"",E18*F18) | H18: 📐 Schneider / Hager / Legrand / ABB
A19: 3.2.4 | B19: SMDB-SH03: wall-mounted SMDB, IP31 powder-coated mild-steel enclosure with padlockable hinged door, 415 V / 3P+N+E, 40A TP MCCB ≥35 kA Icu incomer, busbar 40 A Cu electro-tin plated, Form 2b separation, neutral / earth bars, outgoing MCCBs / MCBs / RCBOs as per SLD, MEB sub-bar bonded to building MEB, ID-engraved circuit labels, padlockable hinged door, manufacturer's factory acceptance test (FAT) certificate. Fire-rated cable glands + LSZH gland-kits at all FR feeder terminations. Connected load 15 kW. Supply, install, terminate, energise, witnessed routine test. | C19: P-201 (SLD) | D19: Nr | E19: 1 | F19: 6000 | G19: =IF(OR(E19="",F19=""),"",E19*F19) | H19: 📐 Schneider / Hager / Legrand / ABB
A20: 3.2.5 | B20: SMDB-SH04: wall-mounted SMDB, IP31 powder-coated mild-steel enclosure with padlockable hinged door, 415 V / 3P+N+E, 40A TP MCCB ≥35 kA Icu incomer, busbar 40 A Cu electro-tin plated, Form 2b separation, neutral / earth bars, outgoing MCCBs / MCBs / RCBOs as per SLD, MEB sub-bar bonded to building MEB, ID-engraved circuit labels, padlockable hinged door, manufacturer's factory acceptance test (FAT) certificate. Fire-rated cable glands + LSZH gland-kits at all FR feeder terminations. Connected load 15 kW. Supply, install, terminate, energise, witnessed routine test. | C20: P-201 (SLD) | D20: Nr | E20: 1 | F20: 6000 | G20: =IF(OR(E20="",F20=""),"",E20*F20) | H20: 📐 Schneider / Hager / Legrand / ABB
A21: 3.2.6 | B21: SMDB-SH05: wall-mounted SMDB, IP31 powder-coated mild-steel enclosure with padlockable hinged door, 415 V / 3P+N+E, 40A TP MCCB ≥35 kA Icu incomer, busbar 40 A Cu electro-tin plated, Form 2b separation, neutral / earth bars, outgoing MCCBs / MCBs / RCBOs as per SLD, MEB sub-bar bonded to building MEB, ID-engraved circuit labels, padlockable hinged door, manufacturer's factory acceptance test (FAT) certificate. Fire-rated cable glands + LSZH gland-kits at all FR feeder terminations. Connected load 25 kW. Supply, install, terminate, energise, witnessed routine test. | C21: P-201 (SLD) | D21: Nr | E21: 1 | F21: 6000 | G21: =IF(OR(E21="",F21=""),"",E21*F21) | H21: 📐 Schneider / Hager / Legrand / ABB
A22: 3.2.7 | B22: SMDB-SH06: wall-mounted SMDB, IP31 powder-coated mild-steel enclosure with padlockable hinged door, 415 V / 3P+N+E, 40A TP MCCB ≥35 kA Icu incomer, busbar 40 A Cu electro-tin plated, Form 2b separation, neutral / earth bars, outgoing MCCBs / MCBs / RCBOs as per SLD, MEB sub-bar bonded to building MEB, ID-engraved circuit labels, padlockable hinged door, manufacturer's factory acceptance test (FAT) certificate. Fire-rated cable glands + LSZH gland-kits at all FR feeder terminations. Connected load 10 kW. Supply, install, terminate, energise, witnessed routine test. | C22: P-201 (SLD) | D22: Nr | E22: 1 | F22: 6000 | G22: =IF(OR(E22="",F22=""),"",E22*F22) | H22: 📐 Schneider / Hager / Legrand / ABB
A23: 3.2.8 | B23: SMDB-SH07: wall-mounted SMDB, IP31 powder-coated mild-steel enclosure with padlockable hinged door, 415 V / 3P+N+E, 40A TP MCCB ≥35 kA Icu incomer, busbar 40 A Cu electro-tin plated, Form 2b separation, neutral / earth bars, outgoing MCCBs / MCBs / RCBOs as per SLD, MEB sub-bar bonded to building MEB, ID-engraved circuit labels, padlockable hinged door, manufacturer's factory acceptance test (FAT) certificate. Fire-rated cable glands + LSZH gland-kits at all FR feeder terminations. Connected load 10 kW. Supply, install, terminate, energise, witnessed routine test. | C23: P-201 (SLD) | D23: Nr | E23: 1 | F23: 6000 | G23: =IF(OR(E23="",F23=""),"",E23*F23) | H23: 📐 Schneider / Hager / Legrand / ABB
A24: 3.2.9 | B24: SMDB-SH08: wall-mounted SMDB, IP31 powder-coated mild-steel enclosure with padlockable hinged door, 415 V / 3P+N+E, 40A TP MCCB ≥35 kA Icu incomer, busbar 40 A Cu electro-tin plated, Form 2b separation, neutral / earth bars, outgoing MCCBs / MCBs / RCBOs as per SLD, MEB sub-bar bonded to building MEB, ID-engraved circuit labels, padlockable hinged door, manufacturer's factory acceptance test (FAT) certificate. Fire-rated cable glands + LSZH gland-kits at all FR feeder terminations. Connected load 40 kW. Supply, install, terminate, energise, witnessed routine test. | C24: P-201 (SLD) | D24: Nr | E24: 1 | F24: 6000 | G24: =IF(OR(E24="",F24=""),"",E24*F24) | H24: 📐 Schneider / Hager / Legrand / ABB
A25: 3.2.10 | B25: SMDB-SH09: wall-mounted SMDB, IP31 powder-coated mild-steel enclosure with padlockable hinged door, 415 V / 3P+N+E, 40A TP MCCB ≥35 kA Icu incomer, busbar 40 A Cu electro-tin plated, Form 2b separation, neutral / earth bars, outgoing MCCBs / MCBs / RCBOs as per SLD, MEB sub-bar bonded to building MEB, ID-engraved circuit labels, padlockable hinged door, manufacturer's factory acceptance test (FAT) certificate. Fire-rated cable glands + LSZH gland-kits at all FR feeder terminations. Connected load 10 kW. Supply, install, terminate, energise, witnessed routine test. | C25: P-201 (SLD) | D25: Nr | E25: 1 | F25: 6000 | G25: =IF(OR(E25="",F25=""),"",E25*F25) | H25: 📐 Schneider / Hager / Legrand / ABB
A26: 3.2.11 | B26: SMDB-SH10: wall-mounted SMDB, IP31 powder-coated mild-steel enclosure with padlockable hinged door, 415 V / 3P+N+E, 40A TP MCCB ≥35 kA Icu incomer, busbar 40 A Cu electro-tin plated, Form 2b separation, neutral / earth bars, outgoing MCCBs / MCBs / RCBOs as per SLD, MEB sub-bar bonded to building MEB, ID-engraved circuit labels, padlockable hinged door, manufacturer's factory acceptance test (FAT) certificate. Fire-rated cable glands + LSZH gland-kits at all FR feeder terminations. Connected load 15 kW. Supply, install, terminate, energise, witnessed routine test. | C26: P-201 (SLD) | D26: Nr | E26: 1 | F26: 6000 | G26: =IF(OR(E26="",F26=""),"",E26*F26) | H26: 📐 Schneider / Hager / Legrand / ABB
A27: 3.2.12 | B27: SMDB-SH11: wall-mounted SMDB, IP31 powder-coated mild-steel enclosure with padlockable hinged door, 415 V / 3P+N+E, 40A TP MCCB ≥35 kA Icu incomer, busbar 40 A Cu electro-tin plated, Form 2b separation, neutral / earth bars, outgoing MCCBs / MCBs / RCBOs as per SLD, MEB sub-bar bonded to building MEB, ID-engraved circuit labels, padlockable hinged door, manufacturer's factory acceptance test (FAT) certificate. Fire-rated cable glands + LSZH gland-kits at all FR feeder terminations. Connected load 15 kW. Supply, install, terminate, energise, witnessed routine test. | C27: P-201 (SLD) | D27: Nr | E27: 1 | F27: 6000 | G27: =IF(OR(E27="",F27=""),"",E27*F27) | H27: 📐 Schneider / Hager / Legrand / ABB
A28: 3.2.13 | B28: SMDB-SH12: wall-mounted SMDB, IP31 powder-coated mild-steel enclosure with padlockable hinged door, 415 V / 3P+N+E, 63A TP MCCB ≥35 kA Icu incomer, busbar 63 A Cu electro-tin plated, Form 2b separation, neutral / earth bars, outgoing MCCBs / MCBs / RCBOs as per SLD, MEB sub-bar bonded to building MEB, ID-engraved circuit labels, padlockable hinged door, manufacturer's factory acceptance test (FAT) certificate. Fire-rated cable glands + LSZH gland-kits at all FR feeder terminations. Connected load 30 kW. Supply, install, terminate, energise, witnessed routine test. | C28: P-201 (SLD) | D28: Nr | E28: 1 | F28: 9000 | G28: =IF(OR(E28="",F28=""),"",E28*F28) | H28: 📐 Schneider / Hager / Legrand / ABB
A29: Sub-Total 3.2 | G29: =SUM(G16:G29)
A31: 3.3 — ROOF SMDBs
A32: 3.3.1 | B32: SMDB-RF: floor-standing SMDB, IP65 stainless-steel 316L weatherproof enclosure with UV-resistant gland kits and sun-shield canopy, 415 V / 3P+N+E, 500A TP MCCB ≥35 kA Icu incomer, busbar 500 A Cu electro-tin plated, Form 2b separation, neutral / earth bars, outgoing MCCBs / MCBs / RCBOs as per SLD, MEB sub-bar bonded to building MEB, ID-engraved circuit labels, padlockable hinged door, manufacturer's factory acceptance test (FAT) certificate. Fire-rated cable glands + LSZH gland-kits at all FR feeder terminations. Connected load 248.63 kW. Supply, install, terminate, energise, witnessed routine test. | C32: P-201 (SLD) / P-106 (Roof) | D32: Nr | E32: 1 | F32: 79200 | G32: =IF(OR(E32="",F32=""),"",E32*F32) | H32: 📐 Schneider / Hager / Legrand / ABB
A33: Sub-Total 3.3 | G33: =SUM(G32:G33)
A35: 3.4 — SPECIAL-DUTY SMDBs (EV / Lift / etc.)
A36: 3.4.1 | B36: SMDB-EV: wall-mounted SMDB, IP54 powder-coated mild-steel enclosure (epoxy-polyester finish), splash + dust-protected, 415 V / 3P+N+E, 160A TP MCCB ≥35 kA Icu incomer, busbar 160 A Cu electro-tin plated, Form 2b separation, neutral / earth bars, outgoing MCCBs / MCBs / RCBOs as per SLD, MEB sub-bar bonded to building MEB, ID-engraved circuit labels, padlockable hinged door, manufacturer's factory acceptance test (FAT) certificate. Fire-rated cable glands + LSZH gland-kits at all FR feeder terminations. Connected load 88 kW. Supply, install, terminate, energise, witnessed routine test. | C36: P-201 (SLD) / P-101 (Basement) | D36: Nr | E36: 1 | F36: 16520 | G36: =IF(OR(E36="",F36=""),"",E36*F36) | H36: 📐 Schneider / Hager / Legrand / ABB
A37: Sub-Total 3.4 | G37: =SUM(G36:G37)
A39: 3.5 — RETAIL SMDBs
A40: 3.5.1 | B40: SMDB-SH01: wall-mounted SMDB, IP31 powder-coated mild-steel enclosure with padlockable hinged door, 415 V / 3P+N+E, 40A TP MCCB ≥35 kA Icu incomer, busbar 40 A Cu electro-tin plated, Form 2b separation, neutral / earth bars, outgoing MCCBs / MCBs / RCBOs as per SLD, MEB sub-bar bonded to building MEB, ID-engraved circuit labels, padlockable hinged door, manufacturer's factory acceptance test (FAT) certificate. Fire-rated cable glands + LSZH gland-kits at all FR feeder terminations. Connected load 15 kW. Supply, install, terminate, energise, witnessed routine test. | C40: P-201 (SLD) | D40: Nr | E40: 1 | F40: 6000 | G40: =IF(OR(E40="",F40=""),"",E40*F40) | H40: 📐 Schneider / Hager / Legrand / ABB
A41: 3.5.2 | B41: SMDB-SH02: wall-mounted SMDB, IP31 powder-coated mild-steel enclosure with padlockable hinged door, 415 V / 3P+N+E, 40A TP MCCB ≥35 kA Icu incomer, busbar 40 A Cu electro-tin plated, Form 2b separation, neutral / earth bars, outgoing MCCBs / MCBs / RCBOs as per SLD, MEB sub-bar bonded to building MEB, ID-engraved circuit labels, padlockable hinged door, manufacturer's factory acceptance test (FAT) certificate. Fire-rated cable glands + LSZH gland-kits at all FR feeder terminations. Connected load 15 kW. Supply, install, terminate, energise, witnessed routine test. | C41: P-201 (SLD) | D41: Nr | E41: 1 | F41: 6000 | G41: =IF(OR(E41="",F41=""),"",E41*F41) | H41: 📐 Schneider / Hager / Legrand / ABB
A42: 3.5.3 | B42: SMDB-SH03: wall-mounted SMDB, IP31 powder-coated mild-steel enclosure with padlockable hinged door, 415 V / 3P+N+E, 40A TP MCCB ≥35 kA Icu incomer, busbar 40 A Cu electro-tin plated, Form 2b separation, neutral / earth bars, outgoing MCCBs / MCBs / RCBOs as per SLD, MEB sub-bar bonded to building MEB, ID-engraved circuit labels, padlockable hinged door, manufacturer's factory acceptance test (FAT) certificate. Fire-rated cable glands + LSZH gland-kits at all FR feeder terminations. Connected load 15 kW. Supply, install, terminate, energise, witnessed routine test. | C42: P-201 (SLD) | D42: Nr | E42: 1 | F42: 6000 | G42: =IF(OR(E42="",F42=""),"",E42*F42) | H42: 📐 Schneider / Hager / Legrand / ABB
A43: 3.5.4 | B43: SMDB-SH04: wall-mounted SMDB, IP31 powder-coated mild-steel enclosure with padlockable hinged door, 415 V / 3P+N+E, 40A TP MCCB ≥35 kA Icu incomer, busbar 40 A Cu electro-tin plated, Form 2b separation, neutral / earth bars, outgoing MCCBs / MCBs / RCBOs as per SLD, MEB sub-bar bonded to building MEB, ID-engraved circuit labels, padlockable hinged door, manufacturer's factory acceptance test (FAT) certificate. Fire-rated cable glands + LSZH gland-kits at all FR feeder terminations. Connected load 15 kW. Supply, install, terminate, energise, witnessed routine test. | C43: P-201 (SLD) | D43: Nr | E43: 1 | F43: 6000 | G43: =IF(OR(E43="",F43=""),"",E43*F43) | H43: 📐 Schneider / Hager / Legrand / ABB
A44: 3.5.5 | B44: SMDB-SH05: wall-mounted SMDB, IP31 powder-coated mild-steel enclosure with padlockable hinged door, 415 V / 3P+N+E, 40A TP MCCB ≥35 kA Icu incomer, busbar 40 A Cu electro-tin plated, Form 2b separation, neutral / earth bars, outgoing MCCBs / MCBs / RCBOs as per SLD, MEB sub-bar bonded to building MEB, ID-engraved circuit labels, padlockable hinged door, manufacturer's factory acceptance test (FAT) certificate. Fire-rated cable glands + LSZH gland-kits at all FR feeder terminations. Connected load 25 kW. Supply, install, terminate, energise, witnessed routine test. | C44: P-201 (SLD) | D44: Nr | E44: 1 | F44: 6000 | G44: =IF(OR(E44="",F44=""),"",E44*F44) | H44: 📐 Schneider / Hager / Legrand / ABB
A45: 3.5.6 | B45: SMDB-SH06: wall-mounted SMDB, IP31 powder-coated mild-steel enclosure with padlockable hinged door, 415 V / 3P+N+E, 40A TP MCCB ≥35 kA Icu incomer, busbar 40 A Cu electro-tin plated, Form 2b separation, neutral / earth bars, outgoing MCCBs / MCBs / RCBOs as per SLD, MEB sub-bar bonded to building MEB, ID-engraved circuit labels, padlockable hinged door, manufacturer's factory acceptance test (FAT) certificate. Fire-rated cable glands + LSZH gland-kits at all FR feeder terminations. Connected load 10 kW. Supply, install, terminate, energise, witnessed routine test. | C45: P-201 (SLD) | D45: Nr | E45: 1 | F45: 6000 | G45: =IF(OR(E45="",F45=""),"",E45*F45) | H45: 📐 Schneider / Hager / Legrand / ABB
A46: 3.5.7 | B46: SMDB-SH07: wall-mounted SMDB, IP31 powder-coated mild-steel enclosure with padlockable hinged door, 415 V / 3P+N+E, 40A TP MCCB ≥35 kA Icu incomer, busbar 40 A Cu electro-tin plated, Form 2b separation, neutral / earth bars, outgoing MCCBs / MCBs / RCBOs as per SLD, MEB sub-bar bonded to building MEB, ID-engraved circuit labels, padlockable hinged door, manufacturer's factory acceptance test (FAT) certificate. Fire-rated cable glands + LSZH gland-kits at all FR feeder terminations. Connected load 10 kW. Supply, install, terminate, energise, witnessed routine test. | C46: P-201 (SLD) | D46: Nr | E46: 1 | F46: 6000 | G46: =IF(OR(E46="",F46=""),"",E46*F46) | H46: 📐 Schneider / Hager / Legrand / ABB
A47: 3.5.8 | B47: SMDB-SH08: wall-mounted SMDB, IP31 powder-coated mild-steel enclosure with padlockable hinged door, 415 V / 3P+N+E, 40A TP MCCB ≥35 kA Icu incomer, busbar 40 A Cu electro-tin plated, Form 2b separation, neutral / earth bars, outgoing MCCBs / MCBs / RCBOs as per SLD, MEB sub-bar bonded to building MEB, ID-engraved circuit labels, padlockable hinged door, manufacturer's factory acceptance test (FAT) certificate. Fire-rated cable glands + LSZH gland-kits at all FR feeder terminations. Connected load 40 kW. Supply, install, terminate, energise, witnessed routine test. | C47: P-201 (SLD) | D47: Nr | E47: 1 | F47: 6000 | G47: =IF(OR(E47="",F47=""),"",E47*F47) | H47: 📐 Schneider / Hager / Legrand / ABB
A48: 3.5.9 | B48: SMDB-SH09: wall-mounted SMDB, IP31 powder-coated mild-steel enclosure with padlockable hinged door, 415 V / 3P+N+E, 40A TP MCCB ≥35 kA Icu incomer, busbar 40 A Cu electro-tin plated, Form 2b separation, neutral / earth bars, outgoing MCCBs / MCBs / RCBOs as per SLD, MEB sub-bar bonded to building MEB, ID-engraved circuit labels, padlockable hinged door, manufacturer's factory acceptance test (FAT) certificate. Fire-rated cable glands + LSZH gland-kits at all FR feeder terminations. Connected load 10 kW. Supply, install, terminate, energise, witnessed routine test. | C48: P-201 (SLD) | D48: Nr | E48: 1 | F48: 6000 | G48: =IF(OR(E48="",F48=""),"",E48*F48) | H48: 📐 Schneider / Hager / Legrand / ABB
A49: 3.5.10 | B49: SMDB-SH10: wall-mounted SMDB, IP31 powder-coated mild-steel enclosure with padlockable hinged door, 415 V / 3P+N+E, 40A TP MCCB ≥35 kA Icu incomer, busbar 40 A Cu electro-tin plated, Form 2b separation, neutral / earth bars, outgoing MCCBs / MCBs / RCBOs as per SLD, MEB sub-bar bonded to building MEB, ID-engraved circuit labels, padlockable hinged door, manufacturer's factory acceptance test (FAT) certificate. Fire-rated cable glands + LSZH gland-kits at all FR feeder terminations. Connected load 15 kW. Supply, install, terminate, energise, witnessed routine test. | C49: P-201 (SLD) | D49: Nr | E49: 1 | F49: 6000 | G49: =IF(OR(E49="",F49=""),"",E49*F49) | H49: 📐 Schneider / Hager / Legrand / ABB
A50: 3.5.11 | B50: SMDB-SH11: wall-mounted SMDB, IP31 powder-coated mild-steel enclosure with padlockable hinged door, 415 V / 3P+N+E, 40A TP MCCB ≥35 kA Icu incomer, busbar 40 A Cu electro-tin plated, Form 2b separation, neutral / earth bars, outgoing MCCBs / MCBs / RCBOs as per SLD, MEB sub-bar bonded to building MEB, ID-engraved circuit labels, padlockable hinged door, manufacturer's factory acceptance test (FAT) certificate. Fire-rated cable glands + LSZH gland-kits at all FR feeder terminations. Connected load 15 kW. Supply, install, terminate, energise, witnessed routine test. | C50: P-201 (SLD) | D50: Nr | E50: 1 | F50: 6000 | G50: =IF(OR(E50="",F50=""),"",E50*F50) | H50: 📐 Schneider / Hager / Legrand / ABB
A51: 3.5.12 | B51: SMDB-SH12: wall-mounted SMDB, IP31 powder-coated mild-steel enclosure with padlockable hinged door, 415 V / 3P+N+E, 63A TP MCCB ≥35 kA Icu incomer, busbar 63 A Cu electro-tin plated, Form 2b separation, neutral / earth bars, outgoing MCCBs / MCBs / RCBOs as per SLD, MEB sub-bar bonded to building MEB, ID-engraved circuit labels, padlockable hinged door, manufacturer's factory acceptance test (FAT) certificate. Fire-rated cable glands + LSZH gland-kits at all FR feeder terminations. Connected load 30 kW. Supply, install, terminate, energise, witnessed routine test. | C51: P-201 (SLD) | D51: Nr | E51: 1 | F51: 9000 | G51: =IF(OR(E51="",F51=""),"",E51*F51) | H51: 📐 Schneider / Hager / Legrand / ABB
A52: Sub-Total 3.5 | G52: =SUM(G40:G52)
A54: 3.6 — EMERGENCY SMDBs (Generator-backed, FR)
A55: 3.6.1 | B55: SMDB-1F: floor-standing SMDB, IP31 powder-coated mild-steel enclosure with padlockable hinged door, 415 V / 3P+N+E, 300A TP MCCB ≥35 kA Icu incomer, busbar 300 A Cu electro-tin plated, Form 2b separation, neutral / earth bars, outgoing MCCBs / MCBs / RCBOs as per SLD, MEB sub-bar bonded to building MEB, ID-engraved circuit labels, padlockable hinged door, manufacturer's factory acceptance test (FAT) certificate. Fire-rated cable glands + LSZH gland-kits at all FR feeder terminations. Connected load 150.86 kW. Supply, install, terminate, energise, witnessed routine test. | C55: P-201 (SLD) / P-103 (1F) | D55: Nr | E55: 1 | F55: 32000 | G55: =IF(OR(E55="",F55=""),"",E55*F55) | H55: 📐 Schneider / Hager / Legrand / ABB
A56: 3.6.2 | B56: SMDB-2F: floor-standing SMDB, IP31 powder-coated mild-steel enclosure with padlockable hinged door, 415 V / 3P+N+E, 300A TP MCCB ≥35 kA Icu incomer, busbar 300 A Cu electro-tin plated, Form 2b separation, neutral / earth bars, outgoing MCCBs / MCBs / RCBOs as per SLD, MEB sub-bar bonded to building MEB, ID-engraved circuit labels, padlockable hinged door, manufacturer's factory acceptance test (FAT) certificate. Fire-rated cable glands + LSZH gland-kits at all FR feeder terminations. Connected load 150.86 kW. Supply, install, terminate, energise, witnessed routine test. | C56: P-201 (SLD) / P-104 (2F) | D56: Nr | E56: 1 | F56: 32000 | G56: =IF(OR(E56="",F56=""),"",E56*F56) | H56: 📐 Schneider / Hager / Legrand / ABB
A57: 3.6.3 | B57: SMDB-3F: floor-standing SMDB, IP31 powder-coated mild-steel enclosure with padlockable hinged door, 415 V / 3P+N+E, 300A TP MCCB ≥35 kA Icu incomer, busbar 300 A Cu electro-tin plated, Form 2b separation, neutral / earth bars, outgoing MCCBs / MCBs / RCBOs as per SLD, MEB sub-bar bonded to building MEB, ID-engraved circuit labels, padlockable hinged door, manufacturer's factory acceptance test (FAT) certificate. Fire-rated cable glands + LSZH gland-kits at all FR feeder terminations. Connected load 150.86 kW. Supply, install, terminate, energise, witnessed routine test. | C57: P-201 (SLD) / P-105 (3F) | D57: Nr | E57: 1 | F57: 32000 | G57: =IF(OR(E57="",F57=""),"",E57*F57) | H57: 📐 Schneider / Hager / Legrand / ABB
A58: 3.6.4 | B58: SMDB-4F: floor-standing SMDB, IP31 powder-coated mild-steel enclosure with padlockable hinged door, 415 V / 3P+N+E, 300A TP MCCB ≥35 kA Icu incomer, busbar 300 A Cu electro-tin plated, Form 2b separation, neutral / earth bars, outgoing MCCBs / MCBs / RCBOs as per SLD, MEB sub-bar bonded to building MEB, ID-engraved circuit labels, padlockable hinged door, manufacturer's factory acceptance test (FAT) certificate. Fire-rated cable glands + LSZH gland-kits at all FR feeder terminations. Connected load 150.86 kW. Supply, install, terminate, energise, witnessed routine test. | C58: P-201 (SLD) / P-104 (4F) | D58: Nr | E58: 1 | F58: 32000 | G58: =IF(OR(E58="",F58=""),"",E58*F58) | H58: 📐 Schneider / Hager / Legrand / ABB
A59: 3.6.5 | B59: SMDB-5F: floor-standing SMDB, IP31 powder-coated mild-steel enclosure with padlockable hinged door, 415 V / 3P+N+E, 300A TP MCCB ≥35 kA Icu incomer, busbar 300 A Cu electro-tin plated, Form 2b separation, neutral / earth bars, outgoing MCCBs / MCBs / RCBOs as per SLD, MEB sub-bar bonded to building MEB, ID-engraved circuit labels, padlockable hinged door, manufacturer's factory acceptance test (FAT) certificate. Fire-rated cable glands + LSZH gland-kits at all FR feeder terminations. Connected load 150.86 kW. Supply, install, terminate, energise, witnessed routine test. | C59: P-201 (SLD) / P-105 (5F) | D59: Nr | E59: 1 | F59: 32000 | G59: =IF(OR(E59="",F59=""),"",E59*F59) | H59: 📐 Schneider / Hager / Legrand / ABB
A60: 3.6.6 | B60: SMDB-6F: floor-standing SMDB, IP31 powder-coated mild-steel enclosure with padlockable hinged door, 415 V / 3P+N+E, 300A TP MCCB ≥35 kA Icu incomer, busbar 300 A Cu electro-tin plated, Form 2b separation, neutral / earth bars, outgoing MCCBs / MCBs / RCBOs as per SLD, MEB sub-bar bonded to building MEB, ID-engraved circuit labels, padlockable hinged door, manufacturer's factory acceptance test (FAT) certificate. Fire-rated cable glands + LSZH gland-kits at all FR feeder terminations. Connected load 150.86 kW. Supply, install, terminate, energise, witnessed routine test. | C60: P-201 (SLD) / P-104 (6F) | D60: Nr | E60: 1 | F60: 32000 | G60: =IF(OR(E60="",F60=""),"",E60*F60) | H60: 📐 Schneider / Hager / Legrand / ABB
A61: 3.6.7 | B61: SMDB-7F: floor-standing SMDB, IP31 powder-coated mild-steel enclosure with padlockable hinged door, 415 V / 3P+N+E, 300A TP MCCB ≥35 kA Icu incomer, busbar 300 A Cu electro-tin plated, Form 2b separation, neutral / earth bars, outgoing MCCBs / MCBs / RCBOs as per SLD, MEB sub-bar bonded to building MEB, ID-engraved circuit labels, padlockable hinged door, manufacturer's factory acceptance test (FAT) certificate. Fire-rated cable glands + LSZH gland-kits at all FR feeder terminations. Connected load 150.86 kW. Supply, install, terminate, energise, witnessed routine test. | C61: P-201 (SLD) / P-105 (7F) | D61: Nr | E61: 1 | F61: 32000 | G61: =IF(OR(E61="",F61=""),"",E61*F61) | H61: 📐 Schneider / Hager / Legrand / ABB
A62: 3.6.8 | B62: SMDB-8F: floor-standing SMDB, IP31 powder-coated mild-steel enclosure with padlockable hinged door, 415 V / 3P+N+E, 300A TP MCCB ≥35 kA Icu incomer, busbar 300 A Cu electro-tin plated, Form 2b separation, neutral / earth bars, outgoing MCCBs / MCBs / RCBOs as per SLD, MEB sub-bar bonded to building MEB, ID-engraved circuit labels, padlockable hinged door, manufacturer's factory acceptance test (FAT) certificate. Fire-rated cable glands + LSZH gland-kits at all FR feeder terminations. Connected load 150.86 kW. Supply, install, terminate, energise, witnessed routine test. | C62: P-201 (SLD) / P-104 (8F) | D62: Nr | E62: 1 | F62: 32000 | G62: =IF(OR(E62="",F62=""),"",E62*F62) | H62: 📐 Schneider / Hager / Legrand / ABB
A63: 3.6.9 | B63: SMDB-RF: floor-standing SMDB, IP65 stainless-steel 316L weatherproof enclosure with UV-resistant gland kits and sun-shield canopy, 415 V / 3P+N+E, 500A TP MCCB ≥35 kA Icu incomer, busbar 500 A Cu electro-tin plated, Form 2b separation, neutral / earth bars, outgoing MCCBs / MCBs / RCBOs as per SLD, MEB sub-bar bonded to building MEB, ID-engraved circuit labels, padlockable hinged door, manufacturer's factory acceptance test (FAT) certificate. Fire-rated cable glands + LSZH gland-kits at all FR feeder terminations. Connected load 248.63 kW. Supply, install, terminate, energise, witnessed routine test. | C63: P-201 (SLD) / P-106 (Roof) | D63: Nr | E63: 1 | F63: 79200 | G63: =IF(OR(E63="",F63=""),"",E63*F63) | H63: 📐 Schneider / Hager / Legrand / ABB
A64: 3.6.10 | B64: SMDB-G: wall-mounted SMDB, IP31 powder-coated mild-steel enclosure with padlockable hinged door, 415 V / 3P+N+E, 125A TP MCCB ≥35 kA Icu incomer, busbar 125 A Cu electro-tin plated, Form 2b separation, neutral / earth bars, outgoing MCCBs / MCBs / RCBOs as per SLD, MEB sub-bar bonded to building MEB, ID-engraved circuit labels, padlockable hinged door, manufacturer's factory acceptance test (FAT) certificate. Fire-rated cable glands + LSZH gland-kits at all FR feeder terminations. Connected load 60.55 kW. Supply, install, terminate, energise, witnessed routine test. | C64: P-201 (SLD) / P-102 (Ground) | D64: Nr | E64: 1 | F64: 14000 | G64: =IF(OR(E64="",F64=""),"",E64*F64) | H64: 📐 Schneider / Hager / Legrand / ABB
A65: 3.6.11 | B65: SMDB-EV: wall-mounted SMDB, IP54 powder-coated mild-steel enclosure (epoxy-polyester finish), splash + dust-protected, 415 V / 3P+N+E, 160A TP MCCB ≥35 kA Icu incomer, busbar 160 A Cu electro-tin plated, Form 2b separation, neutral / earth bars, outgoing MCCBs / MCBs / RCBOs as per SLD, MEB sub-bar bonded to building MEB, ID-engraved circuit labels, padlockable hinged door, manufacturer's factory acceptance test (FAT) certificate. Fire-rated cable glands + LSZH gland-kits at all FR feeder terminations. Connected load 88 kW. Supply, install, terminate, energise, witnessed routine test. | C65: P-201 (SLD) / P-101 (Basement) | D65: Nr | E65: 1 | F65: 16520 | G65: =IF(OR(E65="",F65=""),"",E65*F65) | H65: 📐 Schneider / Hager / Legrand / ABB
A66: 3.6.12 | B66: SMDB-SH01: wall-mounted SMDB, IP31 powder-coated mild-steel enclosure with padlockable hinged door, 415 V / 3P+N+E, 40A TP MCCB ≥35 kA Icu incomer, busbar 40 A Cu electro-tin plated, Form 2b separation, neutral / earth bars, outgoing MCCBs / MCBs / RCBOs as per SLD, MEB sub-bar bonded to building MEB, ID-engraved circuit labels, padlockable hinged door, manufacturer's factory acceptance test (FAT) certificate. Fire-rated cable glands + LSZH gland-kits at all FR feeder terminations. Connected load 15 kW. Supply, install, terminate, energise, witnessed routine test. | C66: P-201 (SLD) | D66: Nr | E66: 1 | F66: 6000 | G66: =IF(OR(E66="",F66=""),"",E66*F66) | H66: 📐 Schneider / Hager / Legrand / ABB
... A79: 3.6.25 | B79: ESMDB-RF: wall-mounted SMDB, IP65 stainless-steel 316L weatherproof enclosure with UV-resistant gland kits and sun-shield canopy, 415 V / 3P+N+E, 160A TP MCCB ≥35 kA Icu incomer, busbar 160 A Cu electro-tin plated, Form 2b separation, neutral / earth bars, outgoing MCCBs / MCBs / RCBOs as per SLD, MEB sub-bar bonded to building MEB, ID-engraved circuit labels, padlockable hinged door, manufacturer's factory acceptance test (FAT) certificate. Fire-rated cable glands + LSZH gland-kits at all FR feeder terminations. Connected load 88.69 kW. Supply, install, terminate, energise, witnessed routine test. | C79: P-201 (SLD) / P-106 (Roof) | D79: Nr | E79: 1 | F79: 26565 | G79: =IF(OR(E79="",F79=""),"",E79*F79) | H79: 📐 Schneider / Hager / Legrand / ABB
A80: Sub-Total 3.6 | G80: =SUM(G55:G80)
A83: BILL 3 — TOTAL CARRIED TO SUMMARY | G83: =SUMIF(G4:G81,"<>")

Sheet Bill 4 - Distribution Boards
A1: BILL No. 4 — DISTRIBUTION BOARDS (DBS) & CONSUMER UNITS
A2: Project: Proposed B+G+8+R Commercial & Residential Building, Plot 6731315, Al Barsha South Third, Dubai, UAE | Job: FA_P379 / CRs B/010/25 | Authority: DEWA (Dubai Electricity & Water Authority)
A3: Item | B3: Description | C3: Reference | D3: Unit | E3: Qty | F3: Rate (AED) | G3: Amount (AED) | H3: Origin / Brand
A4: 4.1 — DISTRIBUTION BOARDS (per cable schedule)
A5: 4.1.1 | B5: DB-G: DB fed from SMDB-G, 63A TP incomer, IP4X. Supply, install, terminate, label, test & commission. | C5: P-201 (SLD) / Floor plan | D5: Nr | E5: 1 | F5: 9000 | G5: =IF(OR(E5="",F5=""),"",E5*F5) | H5: 📐 Schneider / Hager / Legrand / ABB
A6: 4.1.2 | B6: DB-F1: DB fed from SMDB-G, 40A TP incomer, IP4X. Supply, install, terminate, label, test & commission. | C6: P-201 (SLD) / Floor plan | D6: Nr | E6: 1 | F6: 6000 | G6: =IF(OR(E6="",F6=""),"",E6*F6) | H6: 📐 Schneider / Hager / Legrand / ABB
A7: 4.1.3 | B7: DB-F4: DB fed from SMDB-G, 40A TP incomer, IP4X. Supply, install, terminate, label, test & commission. | C7: P-201 (SLD) / Floor plan | D7: Nr | E7: 1 | F7: 6000 | G7: =IF(OR(E7="",F7=""),"",E7*F7) | H7: 📐 Schneider / Hager / Legrand / ABB
A8: 4.1.4 | B8: DB-F5: DB fed from SMDB-G, 40A TP incomer, IP4X. Supply, install, terminate, label, test & commission. | C8: P-201 (SLD) / Floor plan | D8: Nr | E8: 1 | F8: 6000 | G8: =IF(OR(E8="",F8=""),"",E8*F8) | H8: 📐 Schneider / Hager / Legrand / ABB
A9: 4.1.5 | B9: DB-L.GYM: DB fed from SMDB-RF, 40A TP incomer, IP4X. Supply, install, terminate, label, test & commission. | C9: P-106 (Roof) / P-201 (SLD) | D9: Nr | E9: 1 | F9: 6000 | G9: =IF(OR(E9="",F9=""),"",E9*F9) | H9: 📐 Schneider / Hager / Legrand / ABB
A10: 4.1.6 | B10: DB-G.GYM: DB fed from SMDB-RF, 40A TP incomer, IP4X. Supply, install, terminate, label, test & commission. | C10: P-106 (Roof) / P-201 (SLD) | D10: Nr | E10: 1 | F10: 6000 | G10: =IF(OR(E10="",F10=""),"",E10*F10) | H10: 📐 Schneider / Hager / Legrand / ABB
A11: 4.1.7 | B11: DB-WM: DB fed from SMDB-RF, 40A TP incomer, IP4X. Supply, install, terminate, label, test & commission. | C11: P-106 (Roof) / P-201 (SLD) | D11: Nr | E11: 1 | F11: 6000 | G11: =IF(OR(E11="",F11=""),"",E11*F11) | H11: 📐 Schneider / Hager / Legrand / ABB
A12: 4.1.8 | B12: EDB-G: DB fed from ESMDB-G, 40A TP incomer, IP4X. Supply, install, terminate, label, test & commission. | C12: P-201 (Emergency) / Floor plan | D12: Nr | E12: 1 | F12: 6900 | G12: =IF(OR(E12="",F12=""),"",E12*F12) | H12: 📐 Schneider / Hager / Legrand / ABB
A13: 4.1.9 | B13: EDB-1F: DB fed from ESMDB-G, 32A TP incomer, IP4X. Supply, install, terminate, label, test & commission. | C13: P-201 (Emergency) / Floor plan | D13: Nr | E13: 1 | F13: 6900 | G13: =IF(OR(E13="",F13=""),"",E13*F13) | H13: 📐 Schneider / Hager / Legrand / ABB
A14: 4.1.10 | B14: EDB-TEL: DB fed from ESMDB-G, 40A TP incomer, IP4X. Supply, install, terminate, label, test & commission. | C14: P-201 (Emergency) / Floor plan | D14: Nr | E14: 1 | F14: 6900 | G14: =IF(OR(E14="",F14=""),"",E14*F14) | H14: 📐 Schneider / Hager / Legrand / ABB
A15: 4.1.11 | B15: EDB-PR: DB fed from ESMDB-G, 40A TP incomer, IP4X. Supply, install, terminate, label, test & commission. | C15: P-201 (Emergency) / Floor plan | D15: Nr | E15: 1 | F15: 6900 | G15: =IF(OR(E15="",F15=""),"",E15*F15) | H15: 📐 Schneider / Hager / Legrand / ABB
A16: 4.1.12 | B16: EDB-4F: DB fed from ESMDB-RF, 40A TP incomer, IP4X. Supply, install, terminate, label, test & commission. | C16: P-106 (Roof) / P-201 (SLD) | D16: Nr | E16: 1 | F16: 6900 | G16: =IF(OR(E16="",F16=""),"",E16*F16) | H16: 📐 Schneider / Hager / Legrand / ABB
... A60: 4.1.56 | B60: DB-SHOP12: DB fed from SMDB-SH01 to SMDB-SH12, TP incomer, IP4X. Supply, install, terminate, label, test & commission. | C60: P-201 (SLD) / Floor plan | D60: Nr | E60: 1 | F60: 12000 | G60: =IF(OR(E60="",F60=""),"",E60*F60) | H60: 📐 Schneider / Hager / Legrand / ABB
A61: Sub-Total 4.1 | G61: =SUM(G5:G61)
A64: BILL 4 — TOTAL CARRIED TO SUMMARY | G64: =SUMIF(G4:G62,"<>")

Sheet Bill 5 - LV Cables
A1: BILL No. 5 — LV POWER CABLES (Main + Distribution + Final Circuits)
A2: Project: Proposed B+G+8+R Commercial & Residential Building, Plot 6731315, Al Barsha South Third, Dubai, UAE | Job: FA_P379 / CRs B/010/25 | Authority: DEWA (Dubai Electricity & Water Authority)
A3: Item | B3: Cable Size | C3: Description (Route & Scope) | D3: Reference | E3: Unit | F3: Qty | G3: Rate (AED) | H3: Amount (AED) | I3: Origin / Brand
A4: 5.1 — XLPE / SWA / PVC LV CABLES — Plant & Utility Risers (LV Panel → SMDB)
A5: Spec (all rows in this section): XLPE / SWA / PVC 600/1000 V armoured cable to BS 5467 / IEC 60502, on plant / utility risers (non-public-area, non-escape-route). Installed in cable tray / ladder / conduit incl. fire stopping at penetrations, BW-type brass glands with shrouds, compression lugs, ferrules and terminations at both ends.
A6: 5.1.1 | B6: 4C×150mm² XLPE/SWA/PVC | C6: LVP-01 → SMDB-1F — plant / utility riser | D6: P-200 (SLD) / P-010 (Cable tray) | E6: m | F6: 25 | G6: 195 | H6: =IF(OR(F6="",G6=""),"",F6*G6) | I6: 📐 Ducab / NCC / Oman Cables / Riyadh Cables
A7: 5.1.2 | B7: 4C×150mm² XLPE/SWA/PVC | C7: LVP-01 → SMDB-2F — plant / utility riser | D7: P-200 (SLD) / P-010 (Cable tray) | E7: m | F7: 29 | G7: 195 | H7: =IF(OR(F7="",G7=""),"",F7*G7) | I7: 📐 Ducab / NCC / Oman Cables / Riyadh Cables
A8: 5.1.3 | B8: 4C×150mm² XLPE/SWA/PVC | C8: LVP-01 → SMDB-3F — plant / utility riser | D8: P-200 (SLD) / P-010 (Cable tray) | E8: m | F8: 33 | G8: 195 | H8: =IF(OR(F8="",G8=""),"",F8*G8) | I8: 📐 Ducab / NCC / Oman Cables / Riyadh Cables
A9: 5.1.4 | B9: 4C×150mm² XLPE/SWA/PVC | C9: LVP-01 → SMDB-4F — plant / utility riser | D9: P-200 (SLD) / P-010 (Cable tray) | E9: m | F9: 37 | G9: 195 | H9: =IF(OR(F9="",G9=""),"",F9*G9) | I9: 📐 Ducab / NCC / Oman Cables / Riyadh Cables
A10: 5.1.5 | B10: 4C×150mm² XLPE/SWA/PVC | C10: LVP-01 → SMDB-5F — plant / utility riser | D10: P-200 (SLD) / P-010 (Cable tray) | E10: m | F10: 41 | G10: 195 | H10: =IF(OR(F10="",G10=""),"",F10*G10) | I10: 📐 Ducab / NCC / Oman Cables / Riyadh Cables
A11: 5.1.6 | B11: 4C×150mm² XLPE/SWA/PVC | C11: LVP-01 → SMDB-6F — plant / utility riser | D11: P-200 (SLD) / P-010 (Cable tray) | E11: m | F11: 45 | G11: 195 | H11: =IF(OR(F11="",G11=""),"",F11*G11) | I11: 📐 Ducab / NCC / Oman Cables / Riyadh Cables
A12: 5.1.7 | B12: 4C×150mm² XLPE/SWA/PVC | C12: LVP-01 → SMDB-7F — plant / utility riser | D12: P-200 (SLD) / P-010 (Cable tray) | E12: m | F12: 49 | G12: 195 | H12: =IF(OR(F12="",G12=""),"",F12*G12) | I12: 📐 Ducab / NCC / Oman Cables / Riyadh Cables
A13: 5.1.8 | B13: 4C×150mm² XLPE/SWA/PVC | C13: LVP-01 → SMDB-8F — plant / utility riser | D13: P-200 (SLD) / P-010 (Cable tray) | E13: m | F13: 53 | G13: 195 | H13: =IF(OR(F13="",G13=""),"",F13*G13) | I13: 📐 Ducab / NCC / Oman Cables / Riyadh Cables
A14: 5.1.9 | B14: 4C×150mm² XLPE/SWA/PVC | C14: LVP-02 → SMDB-RF — plant / utility riser | D14: P-200 (SLD) / P-010 (Cable tray) | E14: m | F14: 65 | G14: 195 | H14: =IF(OR(F14="",G14=""),"",F14*G14) | I14: 📐 Ducab / NCC / Oman Cables / Riyadh Cables
A15: 5.1.10 | B15: 4C×50mm² XLPE/SWA/PVC | C15: LVP-02 → SMDB-G — plant / utility riser | D15: P-200 (SLD) / P-010 (Cable tray) | E15: m | F15: 15 | G15: 85 | H15: =IF(OR(F15="",G15=""),"",F15*G15) | I15: 📐 Ducab / NCC / Oman Cables / Riyadh Cables
A16: 5.1.11 | B16: 4C×70mm² XLPE/SWA/PVC | C16: LVP-02 → SMDB-EV — plant / utility riser | D16: P-200 (SLD) / P-010 (Cable tray) | E16: m | F16: 20 | G16: 110 | H16: =IF(OR(F16="",G16=""),"",F16*G16) | I16: 📐 Ducab / NCC / Oman Cables / Riyadh Cables
A17: 5.1.12 | B17: 4C×10mm² XLPE/SWA/PVC | C17: LVP-02 → SMDB-SH01 — plant / utility riser | D17: P-200 (SLD) / P-010 (Cable tray) | E17: m | F17: 20 | G17: 22 | H17: =IF(OR(F17="",G17=""),"",F17*G17) | I17: 📐 Ducab / NCC / Oman Cables / Riyadh Cables
... A28: 5.1.23 | B28: 4C×16mm² XLPE/SWA/PVC | C28: LVP-02 → SMDB-SH12 — plant / utility riser | D28: P-200 (SLD) / P-010 (Cable tray) | E28: m | F28: 42 | G28: 32 | H28: =IF(OR(F28="",G28=""),"",F28*G28) | I28: 📐 Ducab / NCC / Oman Cables / Riyadh Cables
A29: Sub-Total 5.1 | H29: =SUM(H6:H29)
A31: 5.2 — FIRE-RATED LSZH CABLES (BS 6387 CWZ / IEC 60331-21 — life-safety circuits)
A32: Spec (all rows in this section): Fire-Rated LSZH cable to BS 6387 CWZ / IEC 60331-21 (950 °C / 3 h circuit integrity); LSZH outer jacket per BS 7211 / IEC 60332-3 Cat C / IEC 61034 / IEC 60754. Dedicated fire-rated containment, FR cleats at max 300 mm centres, FR/LSZH glands, FR terminations, red ID labels.
A33: 5.2.1 | B33: 4C×70mm² FR/LSZH | C33: LVP-02 → ESMDB-G — life-safety circuit | D33: P-200 (SLD) / P-010 (Cable tray) | E33: m | F33: 15 | G33: 229 | H33: =IF(OR(F33="",G33=""),"",F33*G33) | I33: 📐 Ducab FR / Pirelli / Prysmian / Nexans
A34: 5.2.2 | B34: 4C×185mm² FR/LSZH | C34: LVP-02 → Fire Pump — life-safety circuit | D34: P-200 (SLD) / P-010 (Cable tray) | E34: m | F34: 35 | G34: 510 | H34: =IF(OR(F34="",G34=""),"",F34*G34) | I34: 📐 Ducab FR / Pirelli / Prysmian / Nexans
A35: Sub-Total 5.2 | H35: =SUM(H33:H35)
A37: 5.3 — DISTRIBUTION CABLES (SMDB → DB) — XLPE / SWA / PVC
A38: Spec (all rows in this section): XLPE / SWA / PVC 600/1000 V armoured cable to BS 5467 / IEC 60502, on plant / utility risers (non-public-area, non-escape-route). Installed in cable tray / ladder / conduit incl. fire stopping at penetrations, BW-type brass glands with shrouds, compression lugs, ferrules and terminations at both ends.
A39: 5.3.1 | B39: 4C×16mm² XLPE/SWA/PVC | C39: SMDB-G → DB-G — SMDB → DB distribution | D39: P-201 (SLD) / Floor plan | E39: m | F39: 20 | G39: 32 | H39: =IF(OR(F39="",G39=""),"",F39*G39) | I39: 📐 Ducab / NCC / Oman Cables / Riyadh Cables
A40: 5.3.2 | B40: 4C×10mm² XLPE/SWA/PVC | C40: SMDB-G → DB-F1 — SMDB → DB distribution | D40: P-201 (SLD) / Floor plan | E40: m | F40: 15 | G40: 22 | H40: =IF(OR(F40="",G40=""),"",F40*G40) | I40: 📐 Ducab / NCC / Oman Cables / Riyadh Cables
A41: 5.3.3 | B41: 4C×10mm² XLPE/SWA/PVC | C41: SMDB-G → DB-F4 — SMDB → DB distribution | D41: P-201 (SLD) / Floor plan | E41: m | F41: 15 | G41: 22 | H41: =IF(OR(F41="",G41=""),"",F41*G41) | I41: 📐 Ducab / NCC / Oman Cables / Riyadh Cables
A42: 5.3.4 | B42: 4C×10mm² XLPE/SWA/PVC | C42: SMDB-G → DB-F5 — SMDB → DB distribution | D42: P-201 (SLD) / Floor plan | E42: m | F42: 15 | G42: 22 | H42: =IF(OR(F42="",G42=""),"",F42*G42) | I42: 📐 Ducab / NCC / Oman Cables / Riyadh Cables
A43: 5.3.5 | B43: 4C×10mm² XLPE/SWA/PVC | C43: SMDB-RF → DB-L.GYM — SMDB → DB distribution | D43: P-201 (SLD) / Floor plan | E43: m | F43: 20 | G43: 22 | H43: =IF(OR(F43="",G43=""),"",F43*G43) | I43: 📐 Ducab / NCC / Oman Cables / Riyadh Cables
A44: 5.3.6 | B44: 4C×10mm² XLPE/SWA/PVC | C44: SMDB-RF → DB-G.GYM — SMDB → DB distribution | D44: P-201 (SLD) / Floor plan | E44: m | F44: 20 | G44: 22 | H44: =IF(OR(F44="",G44=""),"",F44*G44) | I44: 📐 Ducab / NCC / Oman Cables / Riyadh Cables
A45: 5.3.7 | B45: 4C×10mm² XLPE/SWA/PVC | C45: SMDB-RF → DB-WM — SMDB → DB distribution | D45: P-201 (SLD) / Floor plan | E45: m | F45: 15 | G45: 22 | H45: =IF(OR(F45="",G45=""),"",F45*G45) | I45: 📐 Ducab / NCC / Oman Cables / Riyadh Cables
A46: 5.3.8 | B46: 4C×10mm² XLPE/SWA/PVC | C46: ESMDB-G → EDB-G — SMDB → DB distribution | D46: P-201 (SLD) / Floor plan | E46: m | F46: 15 | G46: 22 | H46: =IF(OR(F46="",G46=""),"",F46*G46) | I46: 📐 Ducab / NCC / Oman Cables / Riyadh Cables
A47: 5.3.9 | B47: 4C×6mm² XLPE/SWA/PVC | C47: ESMDB-G → EDB-1F — SMDB → DB distribution | D47: P-201 (SLD) / Floor plan | E47: m | F47: 25 | G47: 14 | H47: =IF(OR(F47="",G47=""),"",F47*G47) | I47: 📐 Ducab / NCC / Oman Cables / Riyadh Cables
A48: 5.3.10 | B48: 4C×10mm² XLPE/SWA/PVC | C48: ESMDB-G → EDB-TEL — SMDB → DB distribution | D48: P-201 (SLD) / Floor plan | E48: m | F48: 15 | G48: 22 | H48: =IF(OR(F48="",G48=""),"",F48*G48) | I48: 📐 Ducab / NCC / Oman Cables / Riyadh Cables
A49: 5.3.11 | B49: 4C×10mm² XLPE/SWA/PVC | C49: ESMDB-G → EDB-PR — SMDB → DB distribution | D49: P-201 (SLD) / Floor plan | E49: m | F49: 30 | G49: 22 | H49: =IF(OR(F49="",G49=""),"",F49*G49) | I49: 📐 Ducab / NCC / Oman Cables / Riyadh Cables
A50: 5.3.12 | B50: 4C×10mm² XLPE/SWA/PVC | C50: ESMDB-RF → EDB-4F — SMDB → DB distribution | D50: P-201 (SLD) / Floor plan | E50: m | F50: 20 | G50: 22 | H50: =IF(OR(F50="",G50=""),"",F50*G50) | I50: 📐 Ducab / NCC / Oman Cables / Riyadh Cables
... A172: 5.3.134 | B172: 4C×16mm² XLPE/SWA/PVC | C172: SMDB-8F → DB-T15 — SMDB → DB distribution | D172: P-201 (SLD) / Floor plan | E172: m | F172: 25 | G172: 32 | H172: =IF(OR(F172="",G172=""),"",F172*G172) | I172: 📐 Ducab / NCC / Oman Cables / Riyadh Cables
A173: Sub-Total 5.3 | H173: =SUM(H39:H173)
A175: 5.5 — LSZH CABLES — Public-Area & Escape-Route Final Circuits (DCD compliance)
A176: 5.5.1 | B176: LSZH 4C × 16 mm² | C176: Corridor & lobby final-circuit risers, escape-route mains (BS 7211 / IEC 60332-3 Cat C / IEC 61034 / IEC 60754). | D176: P-103 … P-108 / P-201 | E176: m | F176: 220 | G176: 42 | H176: =IF(OR(F176="",G176=""),"",F176*G176) | I176: 📋 Ducab LSZH / Prysmian / Helkama / Nexans
A177: 5.5.2 | B177: LSZH 3C × 4 mm² Cu | C177: Apartment lighting & socket sub-mains in escape corridors. | D177: P-103 … P-108 / P-201 | E177: m | F177: 480 | G177: 11 | H177: =IF(OR(F177="",G177=""),"",F177*G177) | I177: 📋 Ducab LSZH / Prysmian / Helkama / Nexans
A178: 5.5.3 | B178: LSZH 3C × 2.5 mm² Cu | C178: Final-circuit drops to apartment outlets & accessories on escape route. | D178: P-103 … P-108 / P-201 | E178: m | F178: 1200 | G178: 8 | H178: =IF(OR(F178="",G178=""),"",F178*G178) | I178: 📋 Ducab LSZH / Prysmian / Helkama / Nexans
A179: 5.5.4 | B179: LSZH 2C × 1.5 mm² Cu | C179: Emergency / exit-sign final circuits (combined with FR per Bill 5.2). | D179: P-103 … P-108 / P-201 | E179: m | F179: 540 | G179: 7 | H179: =IF(OR(F179="",G179=""),"",F179*G179) | I179: 📋 Ducab FR / Pirelli / Prysmian / Nexans
A180: Sub-Total 5.5 | H180: =SUM(H176:H180)
A182: 5.7 — EARTH CONTINUITY CONDUCTORS (ECC) ALONGSIDE RISING MAINS
A183: 5.7.1 | B183: 1C × 35 mm² G/Y XLPE ECC | C183: Alongside fire-rated rising mains (allowance). | D183: P-200 (SLD) / BS 6004 | E183: m | F183: 50 | G183: 27 | H183: =IF(OR(F183="",G183=""),"",F183*G183) | I183: 📋 Ducab FR / Pirelli / Prysmian / Nexans
A184: 5.7.2 | B184: 1C × 10–70 mm² G/Y XLPE ECC | C184: Alongside XLPE rising mains (allow per run). | D184: P-200 (SLD) / BS 6004 | E184: m | F184: 709 | G184: 30 | H184: =IF(OR(F184="",G184=""),"",F184*G184) | I184: 📋 Ducab / NCC / Oman Cables / Riyadh Cables
A185: Sub-Total 5.7 | H185: =SUM(H183:H185)
A188: BILL 5 — TOTAL CARRIED TO SUMMARY | H188: =SUMIF(H4:H186,"<>")

Sheet Bill 6 - Containment
A1: BILL No. 6 — CABLE CONTAINMENT (TRAY, LADDER, TRUNKING, CONDUIT)
A2: Project: Proposed B+G+8+R Commercial & Residential Building, Plot 6731315, Al Barsha South Third, Dubai, UAE | Job: FA_P379 / CRs B/010/25 | Authority: DEWA (Dubai Electricity & Water Authority)
A3: Item | B3: Description | C3: Reference | D3: Unit | E3: Qty | F3: Rate (AED) | G3: Amount (AED) | H3: Origin / Brand
A4: 6.1 — CABLE TRAYS, LADDERS, TRUNKING & CONDUITS
A5: 6.1.1 | B5: 300mm wide HDGI cable tray — LV room + main vertical risers, hot-dip galvanised to BS EN ISO 1461, c/w supports at max 1.5m centres on horizontal / 1.0m on vertical, brackets, bends, tees, reducers, copplers, fixings, earth bonding straps. | C5: P-010 (Cable tray detail) / P-201 | D5: m | E5: 180 | F5: 385 | G5: =IF(OR(E5="",F5=""),"",E5*F5) | H5: 📋 Marshall Tufflex / Vergokan / Niedax / Eltete
A6: 6.1.2 | B6: 150mm wide HDGI cable tray — SMDB to DB horizontal distribution, hot-dip galvanised to BS EN ISO 1461, c/w supports at max 1.5m centres on horizontal / 1.0m on vertical, brackets, bends, tees, reducers, copplers, fixings, earth bonding straps. | C6: P-010 (Cable tray detail) / P-201 | D6: m | E6: 320 | F6: 195 | G6: =IF(OR(E6="",F6=""),"",E6*F6) | H6: 📋 Marshall Tufflex / Vergokan / Niedax / Eltete
A7: 6.1.3 | B7: 100mm wide HDGI cable tray — branch distribution, hot-dip galvanised to BS EN ISO 1461, c/w supports at max 1.5m centres on horizontal / 1.0m on vertical, brackets, bends, tees, reducers, copplers, fixings, earth bonding straps. | C7: P-010 (Cable tray detail) / P-201 | D7: m | E7: 250 | F7: 160 | G7: =IF(OR(E7="",F7=""),"",E7*F7) | H7: 📋 Marshall Tufflex / Vergokan / Niedax / Eltete
A8: 6.1.4 | B8: 100×100mm GI trunking — riser shafts, hot-dip galvanised to BS EN ISO 1461, c/w supports at max 1.5m centres on horizontal / 1.0m on vertical, brackets, bends, tees, reducers, copplers, fixings, earth bonding straps. | C8: P-010 (Cable tray detail) / P-201 | D8: m | E8: 120 | F8: 160 | G8: =IF(OR(E8="",F8=""),"",E8*F8) | H8: 📋 Marshall Tufflex / Pemsa / Atkore / DSS
A9: 6.1.5 | B9: Ø25mm GI conduit — exposed / mechanical equipment & wet areas, hot-dip galvanised to BS EN ISO 1461, c/w supports at max 1.5m centres on horizontal / 1.0m on vertical, brackets, bends, tees, reducers, copplers, fixings, earth bonding straps. | C9: P-010 (Cable tray detail) / P-201 | D9: m | E9: 600 | F9: 48 | G9: =IF(OR(E9="",F9=""),"",E9*F9) | H9: 📋 Marshall Tufflex / Pemsa / Atkore / DSS
A10: 6.1.6 | B10: Ø25mm PVC conduit — concealed sub-mains, hot-dip galvanised to BS EN ISO 1461, c/w supports at max 1.5m centres on horizontal / 1.0m on vertical, brackets, bends, tees, reducers, copplers, fixings, earth bonding straps. | C10: P-010 (Cable tray detail) / P-201 | D10: m | E10: 2800 | F10: 48 | G10: =IF(OR(E10="",F10=""),"",E10*F10) | H10: 📋 Marshall Tufflex / Pemsa / Atkore / DSS
A11: 6.1.7 | B11: Ø20mm PVC conduit — concealed final circuits to outlets & lighting points, hot-dip galvanised to BS EN ISO 1461, c/w supports at max 1.5m centres on horizontal / 1.0m on vertical, brackets, bends, tees, reducers, copplers, fixings, earth bonding straps. | C11: P-010 (Cable tray detail) / P-201 | D11: m | E11: 9000 | F11: 48 | G11: =IF(OR(E11="",F11=""),"",E11*F11) | H11: 📋 Marshall Tufflex / Pemsa / Atkore / DSS
A12: 6.1.8 | B12: Pull boxes at every 15m of conduit run or two 90° bends (General Note 14), hot-dip galvanised to BS EN ISO 1461, c/w supports at max 1.5m centres on horizontal / 1.0m on vertical, brackets, bends, tees, reducers, copplers, fixings, earth bonding straps. | C12: P-010 (Cable tray detail) / P-201 | D12: Nr | E12: 400 | F12: 24 | G12: =IF(OR(E12="",F12=""),"",E12*F12) | H12: 📋 Marshall Tufflex / Pemsa / Atkore / DSS
A13: Sub-Total 6.1 | G13: =SUM(G5:G13)
A16: BILL 6 — TOTAL CARRIED TO SUMMARY | G16: =SUMIF(G4:G14,"<>")

Sheet Bill 7 - Wiring Devices
A1: BILL No. 7 — WIRING DEVICES & ACCESSORIES
A2: Project: Proposed B+G+8+R Commercial & Residential Building, Plot 6731315, Al Barsha South Third, Dubai, UAE | Job: FA_P379 / CRs B/010/25 | Authority: DEWA (Dubai Electricity & Water Authority)
A3: Item | B3: Description | C3: Reference | D3: Unit | E3: Qty | F3: Rate (AED) | G3: Amount (AED) | H3: Origin / Brand
A4: 7.1 — BASEMENT — SOCKET OUTLETS & SMALL POWER
A5: 7.1.1 | B5: 13A 230V weatherproof IP55 socket outlet | C5: P-103 … P-108 (Floor plans) | D5: Nr | E5: 40 | F5: 95 | G5: =IF(OR(E5="",F5=""),"",E5*F5) | H5: 📋 MK / Schneider / Legrand / Hager
A6: 7.1.2 | B6: 13A 230V SP switched socket outlet (BS 1363) | C6: P-103 … P-108 (Floor plans) | D6: Nr | E6: 16 | F6: 45 | G6: =IF(OR(E6="",F6=""),"",E6*F6) | H6: 📋 MK / Schneider / Legrand / Hager
A7: 7.1.3 | B7: 20A 230V DP switch — water heater / cooker isolation | C7: P-103 … P-108 (Floor plans) | D7: Nr | E7: 6 | F7: 85 | G7: =IF(OR(E7="",F7=""),"",E7*F7) | H7: 📋 MK / Schneider / Legrand / Hager
A8: Sub-Total 7.1 — Basement | G8: =SUM(G5:G8)
A10: 7.2 — GROUND FLOOR — SOCKET OUTLETS & SMALL POWER
A11: 7.2.1 | B11: 13A 230V SP switched socket outlet (BS 1363) | C11: P-103 … P-108 (Floor plans) | D11: Nr | E11: 40 | F11: 45 | G11: =IF(OR(E11="",F11=""),"",E11*F11) | H11: 📋 MK / Schneider / Legrand / Hager
A12: 7.2.2 | B12: 13A 230V twin switched socket outlet (BS 1363) | C12: P-103 … P-108 (Floor plans) | D12: Nr | E12: 28 | G12: =IF(OR(E12="",F12=""),"",E12*F12) | H12: 📋 MK / Schneider / Legrand / Hager
A13: 7.2.3 | B13: 13A 230V weatherproof IP55 socket outlet | C13: P-103 … P-108 (Floor plans) | D13: Nr | E13: 20 | F13: 95 | G13: =IF(OR(E13="",F13=""),"",E13*F13) | H13: 📋 MK / Schneider / Legrand / Hager
A14: 7.2.4 | B14: Floor box — 13A twin socket + RJ45 dual outlet | C14: P-103 … P-108 (Floor plans) | D14: Nr | E14: 18 | F14: 75 | G14: =IF(OR(E14="",F14=""),"",E14*F14) | H14: 📋 MK / Schneider / Legrand / Hager
A15: 7.2.5 | B15: 13A flex outlet for hand dryer (common WCs) | C15: P-103 … P-108 (Floor plans) | D15: Nr | E15: 8 | G15: =IF(OR(E15="",F15=""),"",E15*F15) | H15: 📋 MK / Schneider / Legrand / Hager
A16: 7.2.6 | B16: 13A switched fused spur with neon for FCU (AC indoor unit) | C16: P-103 … P-108 (Floor plans) | D16: Nr | E16: 6 | F16: 45 | G16: =IF(OR(E16="",F16=""),"",E16*F16) | H16: 📋 MK / Schneider / Legrand / Hager
A17: Sub-Total 7.2 — Ground Floor | G17: =SUM(G11:G17)
A19: 7.3 — 1F — SOCKET OUTLETS & SMALL POWER
A20: 7.3.1 | B20: 13A 230V SP switched socket outlet (BS 1363) | C20: P-103 … P-108 (Floor plans) | D20: Nr | E20: 88 | F20: 45 | G20: =IF(OR(E20="",F20=""),"",E20*F20) | H20: 📋 MK / Schneider / Legrand / Hager
A21: 7.3.2 | B21: 13A 230V twin switched socket outlet (BS 1363) | C21: P-103 … P-108 (Floor plans) | D21: Nr | E21: 162 | G21: =IF(OR(E21="",F21=""),"",E21*F21) | H21: 📋 MK / Schneider / Legrand / Hager
A22: 7.3.3 | B22: 13A 230V twin switched socket outlet + USB-A/USB-C ports | C22: P-103 … P-108 (Floor plans) | D22: Nr | E22: 30 | F22: 180 | G22: =IF(OR(E22="",F22=""),"",E22*F22) | H22: 📋 MK / Schneider / Legrand / Hager
A23: 7.3.4 | B23: 13A 230V weatherproof IP55 socket outlet | C23: P-103 … P-108 (Floor plans) | D23: Nr | E23: 30 | F23: 95 | G23: =IF(OR(E23="",F23=""),"",E23*F23) | H23: 📋 MK / Schneider / Legrand / Hager
A24: 7.3.5 | B24: 20A 230V flex outlet for water heater (with neon) | C24: P-103 … P-108 (Floor plans) | D24: Nr | E24: 22 | G24: =IF(OR(E24="",F24=""),"",E24*F24) | H24: 📋 MK / Schneider / Legrand / Hager
A25: 7.3.6 | B25: 20A 230V DP switch — water heater / cooker isolation | C25: P-103 … P-108 (Floor plans) | D25: Nr | E25: 30 | F25: 85 | G25: =IF(OR(E25="",F25=""),"",E25*F25) | H25: 📋 MK / Schneider / Legrand / Hager
A26: 7.3.7 | B26: 13A switched fused spur with neon for FCU (AC indoor unit) | C26: P-103 … P-108 (Floor plans) | D26: Nr | E26: 48 | F26: 45 | G26: =IF(OR(E26="",F26=""),"",E26*F26) | H26: 📋 MK / Schneider / Legrand / Hager
A27: 7.3.8 | B27: 13A flex outlet for gas hob / cooker point | C27: P-103 … P-108 (Floor plans) | D27: Nr | E27: 15 | G27: =IF(OR(E27="",F27=""),"",E27*F27) | H27: 📋 MK / Schneider / Legrand / Hager
A28: Sub-Total 7.3 — 1F | G28: =SUM(G20:G28)
A30: 7.4 — 2F — SOCKET OUTLETS & SMALL POWER
A31: 7.4.1 | B31: 13A 230V SP switched socket outlet (BS 1363) | C31: P-103 … P-108 (Floor plans) | D31: Nr | E31: 88 | F31: 45 | G31: =IF(OR(E31="",F31=""),"",E31*F31) | H31: 📋 MK / Schneider / Legrand / Hager
A32: 7.4.2 | B32: 13A 230V twin switched socket outlet (BS 1363) | C32: P-103 … P-108 (Floor plans) | D32: Nr | E32: 162 | G32: =IF(OR(E32="",F32=""),"",E32*F32) | H32: 📋 MK / Schneider / Legrand / Hager
A33: 7.4.3 | B33: 13A 230V twin switched socket outlet + USB-A/USB-C ports | C33: P-103 … P-108 (Floor plans) | D33: Nr | E33: 30 | F33: 180 | G33: =IF(OR(E33="",F33=""),"",E33*F33) | H33: 📋 MK / Schneider / Legrand / Hager
A34: 7.4.4 | B34: 13A 230V weatherproof IP55 socket outlet | C34: P-103 … P-108 (Floor plans) | D34: Nr | E34: 30 | F34: 95 | G34: =IF(OR(E34="",F34=""),"",E34*F34) | H34: 📋 MK / Schneider / Legrand / Hager
A35: 7.4.5 | B35: 20A 230V flex outlet for water heater (with neon) | C35: P-103 … P-108 (Floor plans) | D35: Nr | E35: 22 | G35: =IF(OR(E35="",F35=""),"",E35*F35) | H35: 📋 MK / Schneider / Legrand / Hager
A36: 7.4.6 | B36: 20A 230V DP switch — water heater / cooker isolation | C36: P-103 … P-108 (Floor plans) | D36: Nr | E36: 30 | F36: 85 | G36: =IF(OR(E36="",F36=""),"",E36*F36) | H36: 📋 MK / Schneider / Legrand / Hager
A37: 7.4.7 | B37: 13A switched fused spur with neon for FCU (AC indoor unit) | C37: P-103 … P-108 (Floor plans) | D37: Nr | E37: 48 | F37: 45 | G37: =IF(OR(E37="",F37=""),"",E37*F37) | H37: 📋 MK / Schneider / Legrand / Hager
A38: 7.4.8 | B38: 13A flex outlet for gas hob / cooker point | C38: P-103 … P-108 (Floor plans) | D38: Nr | E38: 15 | G38: =IF(OR(E38="",F38=""),"",E38*F38) | H38: 📋 MK / Schneider / Legrand / Hager
A39: Sub-Total 7.4 — 2F | G39: =SUM(G31:G39)
A41: 7.5 — 3F — SOCKET OUTLETS & SMALL POWER
A42: 7.5.1 | B42: 13A 230V SP switched socket outlet (BS 1363) | C42: P-103 … P-108 (Floor plans) | D42: Nr | E42: 88 | F42: 45 | G42: =IF(OR(E42="",F42=""),"",E42*F42) | H42: 📋 MK / Schneider / Legrand / Hager
A43: 7.5.2 | B43: 13A 230V twin switched socket outlet (BS 1363) | C43: P-103 … P-108 (Floor plans) | D43: Nr | E43: 162 | G43: =IF(OR(E43="",F43=""),"",E43*F43) | H43: 📋 MK / Schneider / Legrand / Hager
A44: 7.5.3 | B44: 13A 230V twin switched socket outlet + USB-A/USB-C ports | C44: P-103 … P-108 (Floor plans) | D44: Nr | E44: 30 | F44: 180 | G44: =IF(OR(E44="",F44=""),"",E44*F44) | H44: 📋 MK / Schneider / Legrand / Hager
A45: 7.5.4 | B45: 13A 230V weatherproof IP55 socket outlet | C45: P-103 … P-108 (Floor plans) | D45: Nr | E45: 30 | F45: 95 | G45: =IF(OR(E45="",F45=""),"",E45*F45) | H45: 📋 MK / Schneider / Legrand / Hager
A46: 7.5.5 | B46: 20A 230V flex outlet for water heater (with neon) | C46: P-103 … P-108 (Floor plans) | D46: Nr | E46: 22 | G46: =IF(OR(E46="",F46=""),"",E46*F46) | H46: 📋 MK / Schneider / Legrand / Hager
A47: 7.5.6 | B47: 20A 230V DP switch — water heater / cooker isolation | C47: P-103 … P-108 (Floor plans) | D47: Nr | E47: 30 | F47: 85 | G47: =IF(OR(E47="",F47=""),"",E47*F47) | H47: 📋 MK / Schneider / Legrand / Hager
A48: 7.5.7 | B48: 13A switched fused spur with neon for FCU (AC indoor unit) | C48: P-103 … P-108 (Floor plans) | D48: Nr | E48: 48 | F48: 45 | G48: =IF(OR(E48="",F48=""),"",E48*F48) | H48: 📋 MK / Schneider / Legrand / Hager
A49: 7.5.8 | B49: 13A flex outlet for gas hob / cooker point | C49: P-103 … P-108 (Floor plans) | D49: Nr | E49: 15 | G49: =IF(OR(E49="",F49=""),"",E49*F49) | H49: 📋 MK / Schneider / Legrand / Hager
A50: Sub-Total 7.5 — 3F | G50: =SUM(G42:G50)
A52: 7.6 — 4F — SOCKET OUTLETS & SMALL POWER
A53: 7.6.1 | B53: 13A 230V SP switched socket outlet (BS 1363) | C53: P-103 … P-108 (Floor plans) | D53: Nr | E53: 88 | F53: 45 | G53: =IF(OR(E53="",F53=""),"",E53*F53) | H53: 📋 MK / Schneider / Legrand / Hager
A54: 7.6.2 | B54: 13A 230V twin switched socket outlet (BS 1363) | C54: P-103 … P-108 (Floor plans) | D54: Nr | E54: 162 | G54: =IF(OR(E54="",F54=""),"",E54*F54) | H54: 📋 MK / Schneider / Legrand / Hager
A55: 7.6.3 | B55: 13A 230V twin switched socket outlet + USB-A/USB-C ports | C55: P-103 … P-108 (Floor plans) | D55: Nr | E55: 30 | F55: 180 | G55: =IF(OR(E55="",F55=""),"",E55*F55) | H55: 📋 MK / Schneider / Legrand / Hager
A56: 7.6.4 | B56: 13A 230V weatherproof IP55 socket outlet | C56: P-103 … P-108 (Floor plans) | D56: Nr | E56: 30 | F56: 95 | G56: =IF(OR(E56="",F56=""),"",E56*F56) | H56: 📋 MK / Schneider / Legrand / Hager
A57: 7.6.5 | B57: 20A 230V flex outlet for water heater (with neon) | C57: P-103 … P-108 (Floor plans) | D57: Nr | E57: 22 | G57: =IF(OR(E57="",F57=""),"",E57*F57) | H57: 📋 MK / Schneider / Legrand / Hager
A58: 7.6.6 | B58: 20A 230V DP switch — water heater / cooker isolation | C58: P-103 … P-108 (Floor plans) | D58: Nr | E58: 30 | F58: 85 | G58: =IF(OR(E58="",F58=""),"",E58*F58) | H58: 📋 MK / Schneider / Legrand / Hager
A59: 7.6.7 | B59: 13A switched fused spur with neon for FCU (AC indoor unit) | C59: P-103 … P-108 (Floor plans) | D59: Nr | E59: 48 | F59: 45 | G59: =IF(OR(E59="",F59=""),"",E59*F59) | H59: 📋 MK / Schneider / Legrand / Hager
A60: 7.6.8 | B60: 13A flex outlet for gas hob / cooker point | C60: P-103 … P-108 (Floor plans) | D60: Nr | E60: 15 | G60: =IF(OR(E60="",F60=""),"",E60*F60) | H60: 📋 MK / Schneider / Legrand / Hager
A61: Sub-Total 7.6 — 4F | G61: =SUM(G53:G61)
A63: 7.7 — 5F — SOCKET OUTLETS & SMALL POWER
A64: 7.7.1 | B64: 13A 230V SP switched socket outlet (BS 1363) | C64: P-103 … P-108 (Floor plans) | D64: Nr | E64: 88 | F64: 45 | G64: =IF(OR(E64="",F64=""),"",E64*F64) | H64: 📋 MK / Schneider / Legrand / Hager
A65: 7.7.2 | B65: 13A 230V twin switched socket outlet (BS 1363) | C65: P-103 … P-108 (Floor plans) | D65: Nr | E65: 162 | G65: =IF(OR(E65="",F65=""),"",E65*F65) | H65: 📋 MK / Schneider / Legrand / Hager
A66: 7.7.3 | B66: 13A 230V twin switched socket outlet + USB-A/USB-C ports | C66: P-103 … P-108 (Floor plans) | D66: Nr | E66: 30 | F66: 180 | G66: =IF(OR(E66="",F66=""),"",E66*F66) | H66: 📋 MK / Schneider / Legrand / Hager
A67: 7.7.4 | B67: 13A 230V weatherproof IP55 socket outlet | C67: P-103 … P-108 (Floor plans) | D67: Nr | E67: 30 | F67: 95 | G67: =IF(OR(E67="",F67=""),"",E67*F67) | H67: 📋 MK / Schneider / Legrand / Hager
A68: 7.7.5 | B68: 20A 230V flex outlet for water heater (with neon) | C68: P-103 … P-108 (Floor plans) | D68: Nr | E68: 22 | G68: =IF(OR(E68="",F68=""),"",E68*F68) | H68: 📋 MK / Schneider / Legrand / Hager
A69: 7.7.6 | B69: 20A 230V DP switch — water heater / cooker isolation | C69: P-103 … P-108 (Floor plans) | D69: Nr | E69: 30 | F69: 85 | G69: =IF(OR(E69="",F69=""),"",E69*F69) | H69: 📋 MK / Schneider / Legrand / Hager
A70: 7.7.7 | B70: 13A switched fused spur with neon for FCU (AC indoor unit) | C70: P-103 … P-108 (Floor plans) | D70: Nr | E70: 48 | F70: 45 | G70: =IF(OR(E70="",F70=""),"",E70*F70) | H70: 📋 MK / Schneider / Legrand / Hager
A71: 7.7.8 | B71: 13A flex outlet for gas hob / cooker point | C71: P-103 … P-108 (Floor plans) | D71: Nr | E71: 15 | G71: =IF(OR(E71="",F71=""),"",E71*F71) | H71: 📋 MK / Schneider / Legrand / Hager
A72: Sub-Total 7.7 — 5F | G72: =SUM(G64:G72)
A74: 7.8 — 6F — SOCKET OUTLETS & SMALL POWER
A75: 7.8.1 | B75: 13A 230V SP switched socket outlet (BS 1363) | C75: P-103 … P-108 (Floor plans) | D75: Nr | E75: 88 | F75: 45 | G75: =IF(OR(E75="",F75=""),"",E75*F75) | H75: 📋 MK / Schneider / Legrand / Hager
A76: 7.8.2 | B76: 13A 230V twin switched socket outlet (BS 1363) | C76: P-103 … P-108 (Floor plans) | D76: Nr | E76: 162 | G76: =IF(OR(E76="",F76=""),"",E76*F76) | H76: 📋 MK / Schneider / Legrand / Hager
A77: 7.8.3 | B77: 13A 230V twin switched socket outlet + USB-A/USB-C ports | C77: P-103 … P-108 (Floor plans) | D77: Nr | E77: 30 | F77: 180 | G77: =IF(OR(E77="",F77=""),"",E77*F77) | H77: 📋 MK / Schneider / Legrand / Hager
A78: 7.8.4 | B78: 13A 230V weatherproof IP55 socket outlet | C78: P-103 … P-108 (Floor plans) | D78: Nr | E78: 30 | F78: 95 | G78: =IF(OR(E78="",F78=""),"",E78*F78) | H78: 📋 MK / Schneider / Legrand / Hager
A79: 7.8.5 | B79: 20A 230V flex outlet for water heater (with neon) | C79: P-103 … P-108 (Floor plans) | D79: Nr | E79: 22 | G79: =IF(OR(E79="",F79=""),"",E79*F79) | H79: 📋 MK / Schneider / Legrand / Hager
A80: 7.8.6 | B80: 20A 230V DP switch — water heater / cooker isolation | C80: P-103 … P-108 (Floor plans) | D80: Nr | E80: 30 | F80: 85 | G80: =IF(OR(E80="",F80=""),"",E80*F80) | H80: 📋 MK / Schneider / Legrand / Hager
A81: 7.8.7 | B81: 13A switched fused spur with neon for FCU (AC indoor unit) | C81: P-103 … P-108 (Floor plans) | D81: Nr | E81: 48 | F81: 45 | G81: =IF(OR(E81="",F81=""),"",E81*F81) | H81: 📋 MK / Schneider / Legrand / Hager
A82: 7.8.8 | B82: 13A flex outlet for gas hob / cooker point | C82: P-103 … P-108 (Floor plans) | D82: Nr | E82: 15 | G82: =IF(OR(E82="",F82=""),"",E82*F82) | H82: 📋 MK / Schneider / Legrand / Hager
A83: Sub-Total 7.8 — 6F | G83: =SUM(G75:G83)
A85: 7.9 — 7F — SOCKET OUTLETS & SMALL POWER
A86: 7.9.1 | B86: 13A 230V SP switched socket outlet (BS 1363) | C86: P-103 … P-108 (Floor plans) | D86: Nr | E86: 88 | F86: 45 | G86: =IF(OR(E86="",F86=""),"",E86*F86) | H86: 📋 MK / Schneider / Legrand / Hager
A87: 7.9.2 | B87: 13A 230V twin switched socket outlet (BS 1363) | C87: P-103 … P-108 (Floor plans) | D87: Nr | E87: 162 | G87: =IF(OR(E87="",F87=""),"",E87*F87) | H87: 📋 MK / Schneider / Legrand / Hager
A88: 7.9.3 | B88: 13A 230V twin switched socket outlet + USB-A/USB-C ports | C88: P-103 … P-108 (Floor plans) | D88: Nr | E88: 30 | F88: 180 | G88: =IF(OR(E88="",F88=""),"",E88*F88) | H88: 📋 MK / Schneider / Legrand / Hager
A89: 7.9.4 | B89: 13A 230V weatherproof IP55 socket outlet | C89: P-103 … P-108 (Floor plans) | D89: Nr | E89: 30 | F89: 95 | G89: =IF(OR(E89="",F89=""),"",E89*F89) | H89: 📋 MK / Schneider / Legrand / Hager
A90: 7.9.5 | B90: 20A 230V flex outlet for water heater (with neon) | C90: P-103 … P-108 (Floor plans) | D90: Nr | E90: 22 | G90: =IF(OR(E90="",F90=""),"",E90*F90) | H90: 📋 MK / Schneider / Legrand / Hager
A91: 7.9.6 | B91: 20A 230V DP switch — water heater / cooker isolation | C91: P-103 … P-108 (Floor plans) | D91: Nr | E91: 30 | F91: 85 | G91: =IF(OR(E91="",F91=""),"",E91*F91) | H91: 📋 MK / Schneider / Legrand / Hager
A92: 7.9.7 | B92: 13A switched fused spur with neon for FCU (AC indoor unit) | C92: P-103 … P-108 (Floor plans) | D92: Nr | E92: 48 | F92: 45 | G92: =IF(OR(E92="",F92=""),"",E92*F92) | H92: 📋 MK / Schneider / Legrand / Hager
A93: 7.9.8 | B93: 13A flex outlet for gas hob / cooker point | C93: P-103 … P-108 (Floor plans) | D93: Nr | E93: 15 | G93: =IF(OR(E93="",F93=""),"",E93*F93) | H93: 📋 MK / Schneider / Legrand / Hager
A94: Sub-Total 7.9 — 7F | G94: =SUM(G86:G94)
A96: 7.10 — 8F — SOCKET OUTLETS & SMALL POWER
A97: 7.10.1 | B97: 13A 230V SP switched socket outlet (BS 1363) | C97: P-103 … P-108 (Floor plans) | D97: Nr | E97: 88 | F97: 45 | G97: =IF(OR(E97="",F97=""),"",E97*F97) | H97: 📋 MK / Schneider / Legrand / Hager
A98: 7.10.2 | B98: 13A 230V twin switched socket outlet (BS 1363) | C98: P-103 … P-108 (Floor plans) | D98: Nr | E98: 162 | G98: =IF(OR(E98="",F98=""),"",E98*F98) | H98: 📋 MK / Schneider / Legrand / Hager
A99: 7.10.3 | B99: 13A 230V twin switched socket outlet + USB-A/USB-C ports | C99: P-103 … P-108 (Floor plans) | D99: Nr | E99: 30 | F99: 180 | G99: =IF(OR(E99="",F99=""),"",E99*F99) | H99: 📋 MK / Schneider / Legrand / Hager
A100: 7.10.4 | B100: 13A 230V weatherproof IP55 socket outlet | C100: P-103 … P-108 (Floor plans) | D100: Nr | E100: 30 | F100: 95 | G100: =IF(OR(E100="",F100=""),"",E100*F100) | H100: 📋 MK / Schneider / Legrand / Hager
A101: 7.10.5 | B101: 20A 230V flex outlet for water heater (with neon) | C101: P-103 … P-108 (Floor plans) | D101: Nr | E101: 22 | G101: =IF(OR(E101="",F101=""),"",E101*F101) | H101: 📋 MK / Schneider / Legrand / Hager
A102: 7.10.6 | B102: 20A 230V DP switch — water heater / cooker isolation | C102: P-103 … P-108 (Floor plans) | D102: Nr | E102: 30 | F102: 85 | G102: =IF(OR(E102="",F102=""),"",E102*F102) | H102: 📋 MK / Schneider / Legrand / Hager
A103: 7.10.7 | B103: 13A switched fused spur with neon for FCU (AC indoor unit) | C103: P-103 … P-108 (Floor plans) | D103: Nr | E103: 48 | F103: 45 | G103: =IF(OR(E103="",F103=""),"",E103*F103) | H103: 📋 MK / Schneider / Legrand / Hager
A104: 7.10.8 | B104: 13A flex outlet for gas hob / cooker point | C104: P-103 … P-108 (Floor plans) | D104: Nr | E104: 15 | G104: =IF(OR(E104="",F104=""),"",E104*F104) | H104: 📋 MK / Schneider / Legrand / Hager
A105: Sub-Total 7.10 — 8F | G105: =SUM(G97:G105)
A107: 7.11 — ROOF — SOCKET OUTLETS & SMALL POWER
A108: 7.11.1 | B108: 16A industrial socket outlet — BMU provision | C108: P-103 … P-108 (Floor plans) | D108: Nr | E108: 6 | G108: =IF(OR(E108="",F108=""),"",E108*F108) | H108: 📋 MK / Schneider / Legrand / Hager
A109: 7.11.2 | B109: 13A 230V weatherproof IP55 socket outlet | C109: P-103 … P-108 (Floor plans) | D109: Nr | E109: 20 | F109: 95 | G109: =IF(OR(E109="",F109=""),"",E109*F109) | H109: 📋 MK / Schneider / Legrand / Hager
A110: Sub-Total 7.11 — Roof | G110: =SUM(G108:G110)
...

Sheet Bill 8 - Lighting Fixtures
A1: BILL No. 8 — LIGHTING FIXTURES (INTERNAL + EXTERNAL)
A2: Project: Proposed B+G+8+R Commercial & Residential Building, Plot 6731315, Al Barsha South Third, Dubai, UAE | Job: FA_P379 / CRs B/010/25 | Authority: DEWA (Dubai Electricity & Water Authority)
A3: Item | B3: Description | C3: Reference | D3: Unit | E3: Qty | F3: Rate (AED) | G3: Amount (AED) | H3: Origin / Brand
A4: 8.0 — GENERIC ESTIMATE (no fixture legend read from drawings — review against ELV/lighting layout)
A5: 8.1 — INTERIOR LIGHTING — APARTMENTS & COMMON AREAS
A6: 8.1.1 | B6: Recessed LED downlight, 12 W / 800 lm, 4000 K, IP20, anti-glare reflector (apartments, lobby, corridors) | C6: P-103 … P-108 (Floor plans) | D6: Nr | E6: 480 | F6: 85 | G6: =IF(OR(E6="",F6=""),"",E6*F6) | H6: 📋 Philips / Osram / Trilux / Thorn / Cooper
A7: 8.1.2 | B7: Surface-mount LED panel, 600×600 mm, 36 W / 3600 lm, 4000 K (lobby, BOH) | C7: P-103 … P-108 (Floor plans) | D7: Nr | E7: 60 | F7: 640 | G7: =IF(OR(E7="",F7=""),"",E7*F7) | H7: 📋 Philips / Osram / Trilux / Thorn / Cooper
A8: 8.1.3 | B8: Linear LED batten 1200 mm, 36 W / 4000 lm, 4000 K, IP40 (car park, services) | C8: P-103 … P-108 (Floor plans) | D8: Nr | E8: 220 | F8: 640 | G8: =IF(OR(E8="",F8=""),"",E8*F8) | H8: 📋 Philips / Osram / Trilux / Thorn / Cooper
A9: 8.1.4 | B9: Bulkhead LED fitting, 12 W, IP65, polycarbonate (staircase, plant rooms) | C9: P-103 … P-108 (Floor plans) | D9: Nr | E9: 90 | F9: 95 | G9: =IF(OR(E9="",F9=""),"",E9*F9) | H9: 📋 Philips / Osram / Trilux / Thorn / Cooper
A10: 8.1.5 | B10: Wall-mounted LED bracket light (corridors, accent) | C10: P-103 … P-108 (Floor plans) | D10: Nr | E10: 65 | F10: 150 | G10: =IF(OR(E10="",F10=""),"",E10*F10) | H10: 📋 Philips / Osram / Trilux / Thorn / Cooper
A11: 8.1.6 | B11: Pendant decorative LED fixture (lobby — provisional) | C11: P-103 … P-108 (Floor plans) | D11: Nr | E11: 8 | F11: 450 | G11: =IF(OR(E11="",F11=""),"",E11*F11) | H11: 📋 Philips / Osram / Trilux / Thorn / Cooper
A12: 8.1.7 | B12: Track lighting LED spot, 15 W, 3000 K (retail — provisional) | C12: P-103 … P-108 (Floor plans) | D12: Nr | E12: 40 | F12: 140 | G12: =IF(OR(E12="",F12=""),"",E12*F12) | H12: 📋 Philips / Osram / Trilux / Thorn / Cooper
A13: Sub-Total 8.1 | G13: =SUM(G6:G13)
A15: 8.2 — EXTERIOR LIGHTING (Façade, Podium, Parking)
A16: 8.2.1 | B16: External wall-mounted LED fixture, 24 W, IP65, anti-glare optic (podium, façade) | C16: P-100 (Site / external) | D16: Nr | E16: 36 | F16: 280 | G16: =IF(OR(E16="",F16=""),"",E16*F16) | H16: 📋 Philips Lumec / Disano / iGuzzini / Thorn
A17: 8.2.2 | B17: Pole-mounted parking LED area light, 80 W, 4000 K, IP66, on 6 m pole | C17: P-100 (Site / external) | D17: Nr | E17: 14 | F17: 1800 | G17: =IF(OR(E17="",F17=""),"",E17*F17) | H17: 📋 Philips Lumec / Disano / iGuzzini / Thorn
A18: 8.2.3 | B18: Step / kerb LED light, 3 W, IP67, recessed | C18: P-100 (Site / external) | D18: Nr | E18: 28 | F18: 95 | G18: =IF(OR(E18="",F18=""),"",E18*F18) | H18: 📋 Philips Lumec / Disano / iGuzzini / Thorn
A19: 8.2.4 | B19: Bollard LED, 20 W, IP65, 800 mm height (landscape) | C19: P-100 (Site / external) | D19: Nr | E19: 16 | F19: 640 | G19: =IF(OR(E19="",F19=""),"",E19*F19) | H19: 📋 Philips Lumec / Disano / iGuzzini / Thorn
A20: 8.2.5 | B20: Façade LED linear / wall-grazer, IP66 (provisional sum) | C20: P-100 (Site / external) | D20: Sum | E20: 1 | F20: 85000 | G20: =IF(OR(E20="",F20=""),"",E20*F20) | H20: 📋 Philips Lumec / Disano / iGuzzini / Thorn
A21: Sub-Total 8.2 | G21: =SUM(G16:G21)
A23: 8.3 — LIGHTING CONTROLS
A24: 8.3.1 | B24: Time-clock / astronomical timer for façade and external lighting | C24: P-200 (SLD) / Lighting controls | D24: Set | E24: 1 | F24: 85000 | G24: =IF(OR(E24="",F24=""),"",E24*F24) | H24: 📋 Philips Lumec / Disano / iGuzzini / Thorn
A25: 8.3.2 | B25: Photocell / daylight sensor for external circuits | C25: P-200 (SLD) / Lighting controls | D25: Nr | E25: 4 | F25: 250 | G25: =IF(OR(E25="",F25=""),"",E25*F25) | H25: 📋 MK / Schneider / Legrand / Hager
A26: 8.3.3 | B26: DALI/0-10V dimmer module for common-area lighting (provisional) | C26: P-200 (SLD) / Lighting controls | D26: Sum | E26: 1 | F26: 120 | G26: =IF(OR(E26="",F26=""),"",E26*F26) | H26: 📋 Philips / Osram / Trilux / Thorn / Cooper
A27: Sub-Total 8.3 | G27: =SUM(G24:G27)
A30: BILL 8 — TOTAL CARRIED TO SUMMARY | G30: =SUMIF(G4:G28,"<>")

Sheet Bill 9 - Earthing & LP
A1: BILL No. 9 — EARTHING & LIGHTNING PROTECTION
A2: Project: Proposed B+G+8+R Commercial & Residential Building, Plot 6731315, Al Barsha South Third, Dubai, UAE | Job: FA_P379 / CRs B/010/25 | Authority: DEWA (Dubai Electricity & Water Authority)
A3: Item | B3: Description | C3: Reference | D3: Unit | E3: Qty | F3: Rate (AED) | G3: Amount (AED) | H3: Origin / Brand
A4: 9.1 — MAIN EARTHING SYSTEM (TN-S, ≤ 1 Ω)
A5: 9.1.1 | B5: Water-tight double-seal earth pit at basement level c/w 366mmØ seal tube, inspection chamber & low-resistance backfill (resistance test < 1 Ω) | C5: P-300 (LV room) / P-001 (Notes) | D5: Nr | E5: 4 | F5: 510 | G5: =IF(OR(E5="",F5=""),"",E5*F5) | H5: 📋 Erico / Furse / DEHN / Pentair
A6: 9.1.2 | B6: Copper earth rod 17.2mmØ × 3000mm solid copper (per earthing detail) | C6: P-300 (LV room) / P-001 (Notes) | D6: Nr | E6: 4 | F6: 48 | G6: =IF(OR(E6="",F6=""),"",E6*F6) | H6: 📋 Erico / Furse / DEHN / Pentair
A7: 9.1.3 | B7: 1C × 70mm² bare copper main earth conductor — earth pits to Main Earth Bar / DEWA earth terminal | C7: P-300 (LV room) / P-001 (Notes) | D7: m | E7: 120 | F7: 30 | G7: =IF(OR(E7="",F7=""),"",E7*F7) | H7: 📋 Erico / Furse / DEHN / Pentair
A8: 9.1.4 | B8: 1C × 25mm² G/Y earth conductor — MEB to SMDB sub-earth bars and risers | C8: P-300 (LV room) / P-001 (Notes) | D8: m | E8: 350 | F8: 13 | G8: =IF(OR(E8="",F8=""),"",E8*F8) | H8: 📋 Erico / Furse / DEHN / Pentair
A9: 9.1.5 | B9: 1C × 16mm² G/Y earth conductor — SMDB sub-bar to each DB plus cable-tray/trunking bonding | C9: P-300 (LV room) / P-001 (Notes) | D9: m | E9: 800 | F9: 9 | G9: =IF(OR(E9="",F9=""),"",E9*F9) | H9: 📋 Marshall Tufflex / Pemsa / Atkore / DSS
A10: 9.1.6 | B10: Main Earth Bar (MEB) 50×6mm copper busbar in LV room, drilled, insulated, labelled | C10: P-300 (LV room) / P-001 (Notes) | D10: Nr | E10: 2 | F10: 14 | G10: =IF(OR(E10="",F10=""),"",E10*F10) | H10: 📋 Erico / Furse / DEHN / Pentair
A11: 9.1.7 | B11: Surge Protection Device (SPD Type 1+2) at LV panel incomer | C11: P-300 (LV room) / P-001 (Notes) | D11: Nr | E11: 2 | F11: 4500 | G11: =IF(OR(E11="",F11=""),"",E11*F11) | H11: 📋 DEHN / Erico / Furse / Helita
A12: 9.1.8 | B12: Earth bonding of all steel equipment, trays, trunking & supports (per General Note 15/19) | C12: P-300 (LV room) / P-001 (Notes) | D12: Sum | E12: 1 | F12: 65 | G12: =IF(OR(E12="",F12=""),"",E12*F12) | H12: 📋 Marshall Tufflex / Pemsa / Atkore / DSS
A13: Sub-Total 9.1 | G13: =SUM(G5:G13)
A15: 9.2 — LIGHTNING PROTECTION (IEC 62305)
A16: 9.2.1 | B16: Air termination — Franklin/ESE rod, copper-bonded, with insulator + fixing (rooftop) | C16: P-100 (Site) / P-108 (Roof) | D16: Nr | E16: 6 | F16: 1800 | G16: =IF(OR(E16="",F16=""),"",E16*F16) | H16: 📋 DEHN / Erico / Furse / Helita
A17: 9.2.2 | B17: Down conductor — 50mm² bare copper tape/wire, full building height (basement to roof) | C17: P-100 (Site) / P-108 (Roof) | D17: m | E17: 240 | F17: 85 | G17: =IF(OR(E17="",F17=""),"",E17*F17) | H17: 📋 DEHN / Erico / Furse / Helita
A18: 9.2.3 | B18: Test point chamber with disconnector, lockable lid, at base of each down conductor | C18: P-100 (Site) / P-108 (Roof) | D18: Nr | E18: 4 | F18: 1200 | G18: =IF(OR(E18="",F18=""),"",E18*F18) | H18: 📋 DEHN / Erico / Furse / Helita
A19: 9.2.4 | B19: Earth electrode for LP system — copper-bonded rod + inspection chamber | C19: P-100 (Site) / P-108 (Roof) | D19: Nr | E19: 4 | F19: 3500 | G19: =IF(OR(E19="",F19=""),"",E19*F19) | H19: 📋 DEHN / Erico / Furse / Helita
A20: 9.2.5 | B20: Surge protection device (SPD) Type 1+2 at LV panel main incomer | C20: P-100 (Site) / P-108 (Roof) | D20: Nr | E20: 2 | F20: 4500 | G20: =IF(OR(E20="",F20=""),"",E20*F20) | H20: 📋 DEHN / Erico / Furse / Helita
A21: 9.2.6 | B21: Lightning protection design certification, risk assessment per IEC 62305-2 | C21: P-100 (Site) / P-108 (Roof) | D21: Sum | E21: 1 | F21: 8000 | G21: =IF(OR(E21="",F21=""),"",E21*F21) | H21: 📋 DEHN / Erico / Furse / Helita
A22: 9.2.7 | B22: LP testing & DEWA acceptance certificate | C22: P-100 (Site) / P-108 (Roof) | D22: Sum | E22: 1 | F22: 6500 | G22: =IF(OR(E22="",F22=""),"",E22*F22) | H22: 📋 DEHN / Erico / Furse / Helita
A23: Sub-Total 9.2 | G23: =SUM(G16:G23)
A26: BILL 9 — TOTAL CARRIED TO SUMMARY | G26: =SUMIF(G4:G24,"<>")

Sheet Bill 10 - Emergency Lighting
A1: BILL No. 10 — EMERGENCY LIGHTING & LIFE SAFETY
A2: Project: Proposed B+G+8+R Commercial & Residential Building, Plot 6731315, Al Barsha South Third, Dubai, UAE | Job: FA_P379 / CRs B/010/25 | Authority: DEWA (Dubai Electricity & Water Authority)
A3: Item | B3: Description | C3: Reference | D3: Unit | E3: Qty | F3: Rate (AED) | G3: Amount (AED) | H3: Origin / Brand
A4: 10.1 — EMERGENCY LUMINAIRES (3-hour autonomy)
A5: 10.1.1 | B5: Self-contained emergency LED downlight, 3 W, 3-hour duration, IP20, with self-test (corridors, lobbies) | C5: P-103 … P-108 (Floor plans) / P-201 | D5: Nr | E5: 96 | F5: 85 | G5: =IF(OR(E5="",F5=""),"",E5*F5) | H5: 📋 Philips / Osram / Trilux / Thorn / Cooper
A6: 10.1.2 | B6: Self-contained emergency bulkhead, 8 W, 3-hour, IP65 (staircase, plant rooms) | C6: P-103 … P-108 (Floor plans) / P-201 | D6: Nr | E6: 48 | F6: 380 | G6: =IF(OR(E6="",F6=""),"",E6*F6) | H6: 📋 Chloride / Cooper / Tridonic / Hochiki
A7: 10.1.3 | B7: Maintained emergency exit sign LED, single-sided, with arrow pictogram (BS EN 1838) | C7: P-103 … P-108 (Floor plans) / P-201 | D7: Nr | E7: 64 | F7: 320 | G7: =IF(OR(E7="",F7=""),"",E7*F7) | H7: 📋 Chloride / Cooper / Tridonic / Hochiki
A8: 10.1.4 | B8: Maintained emergency exit sign LED, double-sided, ceiling-mounted | C8: P-103 … P-108 (Floor plans) / P-201 | D8: Nr | E8: 18 | F8: 480 | G8: =IF(OR(E8="",F8=""),"",E8*F8) | H8: 📋 Chloride / Cooper / Tridonic / Hochiki
A9: Sub-Total 10.1 | G9: =SUM(G5:G9)
A11: 10.2 — EMERGENCY POWER FOR LIFE-SAFETY EQUIPMENT (FR feeders)
A12: 10.2.1 | B12: Power supply for fire pump panel — Fire-Rated cable from ESMDB-RF, including isolator & terminations | C12: P-200 (Essential) / P-201 (FR feeders) | D12: Set | E12: 1 | F12: 13800 | G12: =IF(OR(E12="",F12=""),"",E12*F12) | H12: 📋 MK / Schneider / Legrand / Hager
A13: 10.2.2 | B13: Power supply for stair pressurisation fans — FR feeder & isolator | C13: P-200 (Essential) / P-201 (FR feeders) | D13: Set | E13: 1 | F13: 110 | G13: =IF(OR(E13="",F13=""),"",E13*F13) | H13: 📋 MK / Schneider / Legrand / Hager
A14: 10.2.3 | B14: Power supply for smoke-extract fans (basement & corridors) — FR feeder & isolator | C14: P-200 (Essential) / P-201 (FR feeders) | D14: Set | E14: 1 | F14: 110 | G14: =IF(OR(E14="",F14=""),"",E14*F14) | H14: 📋 MK / Schneider / Legrand / Hager
A15: 10.2.4 | B15: Power supply for sprinkler-system jockey pump & main pump motor starter | C15: P-200 (Essential) / P-201 (FR feeders) | D15: Set | E15: 1 | F15: 22000 | G15: =IF(OR(E15="",F15=""),"",E15*F15) | H15: 📋
A16: 10.2.5 | B16: Power supply for fire-fighter's lift (2-hour FR feeder) | C16: P-200 (Essential) / P-201 (FR feeders) | D16: Set | E16: 1 | F16: 28000 | G16: =IF(OR(E16="",F16=""),"",E16*F16) | H16: 📋
A17: Sub-Total 10.2 | G17: =SUM(G12:G17)
A19: 10.3 — CENTRAL BATTERY SYSTEM (CBS) — alternative to self-contained
A20: 10.3.1 | B20: CBS cabinet — 24/48 V DC, 3-hour autonomy, sized for total emergency luminaire load (~8 kW for this project), VRLA sealed batteries, charger, supervision, BMS interface, IP31, lockable. Provisional sum. | C20: P-201 (Emergency loop) / P-300 (CBS cabinet) | D20: Sum | E20: 1 | F20: 85000 | G20: =IF(OR(E20="",F20=""),"",E20*F20) | H20: 📋 Chloride / Cooper / Olympia / Hochiki
A21: 10.3.2 | B21: Maintained-feed sub-circuits from CBS to corridor / public-area luminaires — Fire-Rated cable in dedicated FR containment, ID-labelled in red (allow per riser). | C21: P-201 (Emergency loop) / P-300 (CBS cabinet) | D21: m | E21: 180 | F21: 38 | G21: =IF(OR(E21="",F21=""),"",E21*F21) | H21: 📋 Chloride / Cooper / Olympia / Hochiki
A22: 10.3.3 | B22: CBS testing & 3-hour discharge witness test — under controlled outage, recording lumen output and battery voltage decay. | C22: P-201 (Emergency loop) / P-300 (CBS cabinet) | D22: Sum | E22: 1 | F22: 8500 | G22: =IF(OR(E22="",F22=""),"",E22*F22) | H22: 📋
A23: Sub-Total 10.3 | G23: =SUM(G20:G23)
A25: 10.4 — FIRE ALARM / MEP INTEGRATION (DCD requirement)
A26: 10.4.1 | B26: Shunt-trip relay for FAHU isolation on Fire Alarm activation — 24 V DC monitored coil, status feedback to FACP, MCCB shunt-trip module. | C26: Coordinate with FA contractor (FA-001 series) | D26: Nr | E26: 1 | F26: 1800 | G26: =IF(OR(E26="",F26=""),"",E26*F26) | H26: 📋 Schneider / ABB / Siemens / Eaton
A27: 10.4.2 | B27: Shunt-trip relay for AHU isolation per air-handling zone — 24 V DC monitored, status feedback to FACP. (Allow per AHU zone — typical per floor) | C27: Coordinate with FA contractor (FA-001 series) | D27: Nr | E27: 8 | F27: 1800 | G27: =IF(OR(E27="",F27=""),"",E27*F27) | H27: 📋 Schneider / ABB / Siemens / Eaton
A28: 10.4.3 | B28: Lift fire-recall interface module — homes lifts to designated fire-recall floor on Fire Alarm signal, monitored by FACP. (Per lift bank) | C28: Coordinate with FA contractor (FA-001 series) | D28: Nr | E28: 4 | F28: 6500 | G28: =IF(OR(E28="",F28=""),"",E28*F28) | H28: 📋 KONE / Otis / Schindler / Mitsubishi (lift OEM)
A29: 10.4.4 | B29: Smoke / fire damper actuator power supply — 24 V DC monitored, with status feedback (allow per damper, including fire dampers and smoke control). | C29: Coordinate with FA contractor (FA-001 series) | D29: Nr | E29: 24 | F29: 1200 | G29: =IF(OR(E29="",F29=""),"",E29*F29) | H29: 📋 Notifier / Honeywell / Edwards / Hochiki
A30: 10.4.5 | B30: Mag-lock door release on fire alarm — fail-safe release, 24 V DC, monitored relay for FACP signalling. (Per access-controlled fire-route door.) | C30: Coordinate with FA contractor (FA-001 series) | D30: Nr | E30: 12 | F30: 950 | G30: =IF(OR(E30="",F30=""),"",E30*F30) | H30: 📋 Notifier / Honeywell / Edwards / Hochiki
A31: 10.4.6 | B31: FA-BMS interface relay rack — wall-mounted enclosure with 24 V DC PSU, monitored output relays for HVAC / lighting / lift signalling to FACP & BMS. | C31: Coordinate with FA contractor (FA-001 series) | D31: Set | E31: 1 | F31: 18000 | G31: =IF(OR(E31="",F31=""),"",E31*F31) | H31: 📋 Notifier / Honeywell / Edwards / Hochiki
A32: 10.4.7 | B32: FA system tie-in cabling — Fire-Rated 2-core control cable from FACP to interface relays / shunt-trips / damper actuators. (Allow per tie-in.) | C32: Coordinate with FA contractor (FA-001 series) | D32: m | E32: 280 | F32: 65 | G32: =IF(OR(E32="",F32=""),"",E32*F32) | H32: 📋 Schneider / ABB / Siemens / Eaton
A33: Sub-Total 10.4 | G33: =SUM(G26:G33)
A36: BILL 10 — TOTAL CARRIED TO SUMMARY | G36: =SUMIF(G4:G34,"<>")

Sheet Bill 11 - ELV Containment
A1: BILL No. 11 — ELV CONTAINMENT (TEL/DATA, CCTV, ACS, MATV, FA)
A2: Project: Proposed B+G+8+R Commercial & Residential Building, Plot 6731315, Al Barsha South Third, Dubai, UAE | Job: FA_P379 / CRs B/010/25 | Authority: DEWA (Dubai Electricity & Water Authority)
A3: Item | B3: Description | C3: Reference | D3: Unit | E3: Qty | F3: Rate (AED) | G3: Amount (AED) | H3: Origin / Brand
A4: 11.1 — ELV CONTAINMENT — PROVISIONAL (specialist trades)
A5: 11.1.1 | B5: Telephone / data containment — uPVC conduit Ø 25 mm + draw wires from MDF/IDF to apartment outlets | C5: P-010 / Specialist trade | D5: m | E5: 1200 | F5: 48 | G5: =IF(OR(E5="",F5=""),"",E5*F5) | H5: 📋 Marshall Tufflex / Pemsa / Atkore / DSS
A6: 11.1.2 | B6: CCTV containment — uPVC conduit Ø 25 mm + draw wires + back-boxes to camera locations | C6: P-010 / Specialist trade | D6: m | E6: 600 | F6: 48 | G6: =IF(OR(E6="",F6=""),"",E6*F6) | H6: 📋 Marshall Tufflex / Pemsa / Atkore / DSS
A7: 11.1.3 | B7: Access Control containment — conduit + wiring trough at every controlled door | C7: P-010 / Specialist trade | D7: m | E7: 350 | F7: 14 | G7: =IF(OR(E7="",F7=""),"",E7*F7) | H7: 📋 Marshall Tufflex / Pemsa / Atkore / DSS
A8: 11.1.4 | B8: MATV / SMATV containment — conduit + draw wires, MDF to apartment TV points | C8: P-010 / Specialist trade | D8: m | E8: 800 | F8: 14 | G8: =IF(OR(E8="",F8=""),"",E8*F8) | H8: 📋 Marshall Tufflex / Pemsa / Atkore / DSS
A9: 11.1.5 | B9: Fire Alarm containment — fire-rated conduit Ø 25/32 mm at all loops, isolator points (specialist supply by FA contractor) | C9: P-010 / Specialist trade | D9: m | E9: 900 | F9: 99 | G9: =IF(OR(E9="",F9=""),"",E9*F9) | H9: 📋 Marshall Tufflex / Pemsa / Atkore / DSS
A10: 11.1.6 | B10: BMS field cabling containment — conduit + tray at every field-device location (specialist supply by BMS contractor) | C10: P-010 / Specialist trade | D10: m | E10: 600 | F10: 14 | G10: =IF(OR(E10="",F10=""),"",E10*F10) | H10: 📋 Marshall Tufflex / Pemsa / Atkore / DSS
A11: 11.1.7 | B11: Audio-Video / Door-entry containment — conduit + back-boxes | C11: P-010 / Specialist trade | D11: m | E11: 250 | F11: 14 | G11: =IF(OR(E11="",F11=""),"",E11*F11) | H11: 📋 Marshall Tufflex / Pemsa / Atkore / DSS
A12: 11.1.8 | B12: ELV main risers — 100×100 mm GI trunking with separators between systems | C12: P-010 / Specialist trade | D12: m | E12: 80 | F12: 160 | G12: =IF(OR(E12="",F12=""),"",E12*F12) | H12: 📋 Marshall Tufflex / Pemsa / Atkore / DSS
A13: Sub-Total 11.1 | G13: =SUM(G5:G13)
A16: BILL 11 — TOTAL CARRIED TO SUMMARY | G16: =SUMIF(G4:G14,"<>")

Sheet Bill 12 - Metering
A1: BILL No. 12 — METERING & MONITORING
A2: Project: Proposed B+G+8+R Commercial & Residential Building, Plot 6731315, Al Barsha South Third, Dubai, UAE | Job: FA_P379 / CRs B/010/25 | Authority: DEWA (Dubai Electricity & Water Authority)
A3: Item | B3: Description | C3: Reference | D3: Unit | E3: Qty | F3: Rate (AED) | G3: Amount (AED) | H3: Origin / Brand
A4: 12.1 — DEWA SMART METERING — Tenant & Landlord (AMI-ready, DEWA Smart Grid Programme)
A5: 12.1.1 | B5: DEWA-approved smart kWh meter, single-phase, AMI-ready (PLC + RF mesh communication), bi-directional metering capability, Class 1 accuracy, sealed, IEC 62052-11 / IEC 62053-21 compliant — for apartment tenants. Includes anti-tamper detection, configurable load-profile recording, remote-read capability. | C5: P-300 (LV room) / DEWA Smart Grid spec | D5: Nr | E5: 120 | F5: 850 | G5: =IF(OR(E5="",F5=""),"",E5*F5) | H5: 📋 Itron / Landis+Gyr / Iskra (DEWA-listed)
A6: 12.1.2 | B6: DEWA-approved smart kWh meter, three-phase, CT-operated, AMI-ready, bi-directional with consumption + export channel for Shams Dubai net metering (where PV applicable), Class 0.5S accuracy, sealed, IEC 62053-22 — for retail / common services / landlord. | C6: P-300 (LV room) / DEWA Smart Grid spec | D6: Nr | E6: 12 | F6: 2400 | G6: =IF(OR(E6="",F6=""),"",E6*F6) | H6: 📋 Itron / Landis+Gyr / Iskra (DEWA-listed)
A7: 12.1.3 | B7: DEWA-approved smart meter cabinet — DEWA Service Connection Specifications compliant, modular, lockable, ventilated, IP31, with sealed access door for DEWA-only opening, RJ-45 / RS-485 communication ports. | C7: P-300 (LV room) / DEWA Smart Grid spec | D7: Nr | E7: 8 | F7: 3200 | G7: =IF(OR(E7="",F7=""),"",E7*F7) | H7: 📋 Itron / Landis+Gyr / Iskra (DEWA-listed)
A8: 12.1.4 | B8: Current transformers (CTs) for smart-meter feeders — Class 0.5S, 250/5 / 400/5 / 630/5 / 2000/5 ratios per panel schedule, sealed, with DEWA-approved label. | C8: P-300 (LV room) / DEWA Smart Grid spec | D8: Set | E8: 1 | F8: 12000 | G8: =IF(OR(E8="",F8=""),"",E8*F8) | H8: 📋 Schneider PowerLogic / Janitza / Carlo Gavazzi
A9: 12.1.5 | B9: AMI head-end / data-concentrator (PLC + RF mesh gateway) — coordination with DEWA where centralised concentrator is supplied by DEWA; provisional allowance for concentrator location, power supply, and back-haul cabling. | C9: P-300 (LV room) / DEWA Smart Grid spec | D9: Sum | E9: 1 | F9: 28000 | G9: =IF(OR(E9="",F9=""),"",E9*F9) | H9: 📋 Itron / Landis+Gyr / Iskra (DEWA-listed)
A10: Sub-Total 12.1 | G10: =SUM(G5:G10)
A12: 12.2 — PANEL METERING, BMS INTEGRATION & MDM COORDINATION
A13: 12.2.1 | B13: Multi-function digital meter (MFM) on LV panel main incomer & outgoing feeders — V/I/P/Q/PF/THD measurement, MODBUS RTU/TCP communication, Class 0.5 accuracy. | C13: P-300 (LV room) / DEWA Smart Grid spec | D13: Nr | E13: 12 | F13: 2800 | G13: =IF(OR(E13="",F13=""),"",E13*F13) | H13: 📋 Schneider PowerLogic / Janitza / Carlo Gavazzi
A14: 12.2.2 | B14: Energy-monitoring software / SCADA package for panel-level metering — head-end software, dashboards, historical data logging — provisional sum. | C14: P-300 (LV room) / DEWA Smart Grid spec | D14: Sum | E14: 1 | F14: 85000 | G14: =IF(OR(E14="",F14=""),"",E14*F14) | H14: 📋 Itron / Landis+Gyr / Iskra (DEWA-listed)
A15: 12.2.3 | B15: DEWA MDM (Meter Data Management) integration — testing of meter-to-MDM connectivity, data validation, and acceptance per DEWA AMI specifications. Provisional sum. | C15: P-300 (LV room) / DEWA Smart Grid spec | D15: Sum | E15: 1 | F15: 25000 | G15: =IF(OR(E15="",F15=""),"",E15*F15) | H15: 📋 Itron / Landis+Gyr / Iskra (DEWA-listed)
A16: 12.2.4 | B16: Wiring, terminations, CT secondaries, communication cabling (RS-485 / Cat6) for panel-level + smart-meter system. | C16: P-300 (LV room) / DEWA Smart Grid spec | D16: Sum | E16: 1 | F16: 18000 | G16: =IF(OR(E16="",F16=""),"",E16*F16) | H16: 📋 Itron / Landis+Gyr / Iskra (DEWA-listed)
A17: 12.2.5 | B17: DEWA-witnessed meter sealing & acceptance — including AMI commissioning and remote-read verification. | C17: P-300 (LV room) / DEWA Smart Grid spec | D17: Sum | E17: 1 | F17: 12000 | G17: =IF(OR(E17="",F17=""),"",E17*F17) | H17: 📋 Itron / Landis+Gyr / Iskra (DEWA-listed)
A18: Sub-Total 12.2 | G18: =SUM(G13:G18)
A21: BILL 12 — TOTAL CARRIED TO SUMMARY | G21: =SUMIF(G4:G19,"<>")

Sheet Bill 13 - Test & Commissioning
A1: BILL No. 13 — TESTING, COMMISSIONING & DEWA APPROVAL
A2: Project: Proposed B+G+8+R Commercial & Residential Building, Plot 6731315, Al Barsha South Third, Dubai, UAE | Job: FA_P379 / CRs B/010/25 | Authority: DEWA (Dubai Electricity & Water Authority)
A3: Item | B3: Description | C3: Reference | D3: Unit | E3: Qty | F3: Rate (AED) | G3: Amount (AED) | H3: Origin / Brand
A4: 13.1 — ROUTINE ELECTRICAL TESTS (Pre-energisation)
A5: 13.1.1 | B5: Insulation resistance testing of all LV cables — 500 V/1000 V Megger, full report. | C5: DEWA / DM / DCD / IEC 60364-6 | D5: Sum | E5: 1 | F5: 18000 | G5: =IF(OR(E5="",F5=""),"",E5*F5) | H5: 📋 — (contractor selection)
A6: 13.1.2 | B6: Continuity & polarity testing of all final circuits. | C6: DEWA / DM / DCD / IEC 60364-6 | D6: Sum | E6: 1 | F6: 12000 | G6: =IF(OR(E6="",F6=""),"",E6*F6) | H6: 📋 — (contractor selection)
A7: 13.1.3 | B7: Earth fault loop impedance testing at every distribution board. | C7: DEWA / DM / DCD / IEC 60364-6 | D7: Sum | E7: 1 | F7: 2400 | G7: =IF(OR(E7="",F7=""),"",E7*F7) | H7: 📋 — (contractor selection)
A8: 13.1.4 | B8: Phase rotation & balance testing at all 3-phase feeders. | C8: DEWA / DM / DCD / IEC 60364-6 | D8: Sum | E8: 1 | F8: 6500 | G8: =IF(OR(E8="",F8=""),"",E8*F8) | H8: 📋 — (contractor selection)
A9: 13.1.5 | B9: RCD testing at all RCD/RCBO-protected circuits. | C9: DEWA / DM / DCD / IEC 60364-6 | D9: Sum | E9: 1 | F9: 5500 | G9: =IF(OR(E9="",F9=""),"",E9*F9) | H9: 📋 — (contractor selection)
A10: Sub-Total 13.1 | G10: =SUM(G5:G10)
A12: 13.2 — SYSTEM COMMISSIONING (Energisation & Performance)
A13: 13.2.1 | B13: ATS changeover testing — simulate mains failure, verify auto-switchover, full load test. | C13: DEWA / DM / DCD / IEC 60364-6 | D13: Sum | E13: 1 | F13: 80000 | G13: =IF(OR(E13="",F13=""),"",E13*F13) | H13: 📋 ABB / Socomec / Cummins / GE
A14: 13.2.2 | B14: Standby generator full-load test — including load bank (if required), 4-hour run, fuel consumption recording. | C14: DEWA / DM / DCD / IEC 60364-6 | D14: Sum | E14: 1 | F14: 28000 | G14: =IF(OR(E14="",F14=""),"",E14*F14) | H14: 📋 Cummins / Caterpillar / FG Wilson / Perkins
A15: 13.2.3 | B15: Power-factor correction verification — record PF before/after capacitor bank energisation, harmonic analysis. | C15: DEWA / DM / DCD / IEC 60364-6 | D15: Sum | E15: 1 | F15: 8500 | G15: =IF(OR(E15="",F15=""),"",E15*F15) | H15: 📋 — (contractor selection)
A16: 13.2.4 | B16: Earthing system resistance test (Megger DET) at every electrode and MEB. | C16: DEWA / DM / DCD / IEC 60364-6 | D16: Sum | E16: 1 | F16: 1200 | G16: =IF(OR(E16="",F16=""),"",E16*F16) | H16: 📋 Erico / Furse / DEHN / Pentair
A17: 13.2.5 | B17: Lightning protection continuity test, including down-conductor resistance. | C17: DEWA / DM / DCD / IEC 60364-6 | D17: Sum | E17: 1 | F17: 5500 | G17: =IF(OR(E17="",F17=""),"",E17*F17) | H17: 📋 DEHN / Erico / Furse / Helita
A18: 13.2.6 | B18: Emergency lighting 3-hour duration test under controlled outage. | C18: DEWA / DM / DCD / IEC 60364-6 | D18: Sum | E18: 1 | F18: 4500 | G18: =IF(OR(E18="",F18=""),"",E18*F18) | H18: 📋 — (contractor selection)
A19: Sub-Total 13.2 | G19: =SUM(G13:G19)
A21: 13.3 — AUTHORITY APPROVALS & AS-BUILT DOCUMENTATION
A22: 13.3.1 | B22: DEWA Inspection Coordination — coordinating multiple DEWA inspection visits during construction (cable rough-in, panel termination, earthing, metering pre-energisation, energising, post-energisation), submission of inspection requests, attendance, and rectifications until each stage is signed off. | C22: DEWA / DM / DCD / IEC 60364-6 | D22: Sum | E22: 1 | F22: 35000 | G22: =IF(OR(E22="",F22=""),"",E22*F22) | H22: 📋 DEWA / DM / DCD / RTA
A23: 13.3.2 | B23: DEWA Final Approval & Energisation — application fees, witnessed routine test, meter sealing, energising-permit issue. Provisional sum. | C23: DEWA / DM / DCD / IEC 60364-6 | D23: Sum | E23: 1 | F23: 50000 | G23: =IF(OR(E23="",F23=""),"",E23*F23) | H23: 📋 DEWA / DM / DCD / RTA
A24: 13.3.3 | B24: Dubai Municipality (DM) electrical inspection clearance — coordination with DM inspectors, attendance, and rectifications until clearance is obtained for occupancy / completion certificate. | C24: DEWA / DM / DCD / IEC 60364-6 | D24: Sum | E24: 1 | F24: 18000 | G24: =IF(OR(E24="",F24=""),"",E24*F24) | H24: 📋 DEWA / DM / DCD / RTA
A25: 13.3.4 | B25: DCD (Dubai Civil Defence) electrical clearance for life-safety installations — emergency lighting witnessed test, fire-pump power-supply inspection, smoke-control fan circuit verification. | C25: DEWA / DM / DCD / IEC 60364-6 | D25: Sum | E25: 1 | F25: 22000 | G25: =IF(OR(E25="",F25=""),"",E25*F25) | H25: 📋 DEWA / DM / DCD / RTA
A26: 13.3.5 | B26: As-Built Drawings — Consultant Approval. As-Built drawings (AutoCAD .dwg + PDF, 4 hard-copy bound sets), submitted to consultant for review, revisions until approved and signed. | C26: DEWA / DM / DCD / IEC 60364-6 | D26: Sum | E26: 1 | F26: 28000 | G26: =IF(OR(E26="",F26=""),"",E26*F26) | H26: 📋 DEWA / DM / DCD / RTA
A27: 13.3.6 | B27: As-Built Drawings — DEWA Approval. As-Built submission to DEWA in DEWA-required format (specific layer / title-block / electronic file structure), revisions until approved and filed by DEWA. | C27: DEWA / DM / DCD / IEC 60364-6 | D27: Sum | E27: 1 | F27: 32000 | G27: =IF(OR(E27="",F27=""),"",E27*F27) | H27: 📋 DEWA / DM / DCD / RTA
A28: 13.3.7 | B28: Energising application & meter installation coordination with DEWA — preparing application package, submitting to DEWA, attendance at DEWA appointments. | C28: DEWA / DM / DCD / IEC 60364-6 | D28: Sum | E28: 1 | F28: 12000 | G28: =IF(OR(E28="",F28=""),"",E28*F28) | H28: 📋 DEWA / DM / DCD / RTA
A29: 13.3.8 | B29: Final commissioning report — bound, signed, indexed (5 hard copies + electronic PDF), including all routine-test results, manufacturer test certificates, witness signatures. | C29: DEWA / DM / DCD / IEC 60364-6 | D29: Sum | E29: 1 | F29: 22000 | G29: =IF(OR(E29="",F29=""),"",E29*F29) | H29: 📋 DEWA / DM / DCD / RTA
A30: 13.3.9 | B30: Operator training — 2 sessions of 4 hours each, including written training material in English (and Arabic where requested), covering operation, routine maintenance, and emergency response. | C30: DEWA / DM / DCD / IEC 60364-6 | D30: Sum | E30: 1 | F30: 8500 | G30: =IF(OR(E30="",F30=""),"",E30*F30) | H30: 📋 DEWA / DM / DCD / RTA
A31: 13.3.10 | B31: Witnessed handover walk-through with consultant & employer team — verifying every installation against As-Built, snag list, sign-off. | C31: DEWA / DM / DCD / IEC 60364-6 | D31: Sum | E31: 1 | F31: 4500 | G31: =IF(OR(E31="",F31=""),"",E31*F31) | H31: 📋 DEWA / DM / DCD / RTA
A32: Sub-Total 13.3 | G32: =SUM(G22:G32)
A35: BILL 13 — TOTAL CARRIED TO SUMMARY | G35: =SUMIF(G4:G33,"<>")

Sheet Summary of Bills
A1: BILL OF QUANTITIES — SUMMARY OF BILLS
A2: Proposed B+G+8+R Commercial & Residential Building | Plot 6731315, Al Barsha South Third, Dubai, UAE | Job FA_P379 / CRs B/010/25
A4: Bill | B4: Description | C4: Sheet Ref | D4: Bill Total (AED) | E4: Notes
A5: 1 | B5: General Items / Preliminaries | C5: Bill 1 | D5: ='Bill 1 - Preliminaries'!G43 -> 0 | E5: Mob, insurance, submittals, As-Built
A6: 2 | B6: HV / LV Main Distribution | C6: Bill 2 | D6: ='Bill 2 - HV-LV Main'!G20 -> 0 | E6: Transformer, MDB, generator, ATS, capacitors
A7: 3 | B7: Sub-Main Distribution Boards | C7: Bill 3 | D7: ='Bill 3 - SMDBs'!G83 -> 0 | E7: Typical floor, GF, RF, EV, retail, emergency
A8: 4 | B8: Distribution Boards & Consumer Units | C8: Bill 4 | D8: ='Bill 4 - Distribution Boards'!G64 -> 0 | E8: Apt, common, retail, emergency, mech
A9: 5 | B9: LV Power Cables | C9: Bill 5 | D9: ='Bill 5 - LV Cables'!H188 -> 0 | E9: Main + distribution + final + ECC + FR
A10: 6 | B10: Cable Containment | C10: Bill 6 | D10: ='Bill 6 - Containment'!G16 -> 0 | E10: Tray, ladder, conduit, trunking
A11: 7 | B11: Wiring Devices & Accessories | C11: Bill 7 | D11: ='Bill 7 - Wiring Devices'!G129 -> 0 | E11: Sockets, switches, isolators, EV outlets
A12: 8 | B12: Lighting Fixtures | C12: Bill 8 | D12: ='Bill 8 - Lighting Fixtures'!G30 -> 0 | E12: Internal, external, controls
A13: 9 | B13: Earthing & Lightning Protection | C13: Bill 9 | D13: ='Bill 9 - Earthing & LP'!G26 -> 0 | E13: TN-S, electrodes, LP system
A14: 10 | B14: Emergency Lighting & Life Safety | C14: Bill 10 | D14: ='Bill 10 - Emergency Lighting'!G36 -> 0 | E14: Self-contained, exit signs, FR feeders
A15: 11 | B15: ELV Containment | C15: Bill 11 | D15: ='Bill 11 - ELV Containment'!G16 -> 0 | E15: Tel/Data/CCTV/ACS/MATV/FA conduit
A16: 12 | B16: Metering & Monitoring | C16: Bill 12 | D16: ='Bill 12 - Metering'!G21 -> 0 | E16: Tenant + panel meters, BMS integration
A17: 13 | B17: Testing, Commissioning & DEWA Approval | C17: Bill 13 | D17: ='Bill 13 - Test & Commissioning'!G35 -> 0 | E17: Routine tests + system commissioning + DEWA
A18: SUB-TOTAL OF BILLS (Bills 1–13) | D18: =SUM(D5:D17) -> 0
A19: Provisional Sums adjustment (if any) | D19: 0 | E19: Editable — net adjustment
A20: Day Works Schedule (per separate schedule) | D20: 0 | E20: Editable
A21: Contingency (10%) — on Bills 1–13 | D21: =D18*0.1 -> 0
A22: Discount (if offered, enter as negative) | D22: 0 | E22: Editable
A23: TOTAL TENDER PRICE — Excluding VAT | D23: =D18+D19+D20+D21+D22 -> 0
A24: VAT (5%) — UAE Federal Tax Authority | D24: =D23*0.05 -> 0
A25: GRAND TOTAL TENDER PRICE — Including VAT | D25: =D23+D24 -> 0
A27: FORM OF TENDER
A28: We, the undersigned, having examined the tender drawings, specifications, and bill of quantities, do hereby offer to execute the works for the sum stated above (Grand Total Tender Price including VAT).
A29: Validity period: 90 days from tender submission date.
A30: Construction period: as specified in the contract documents.
A31: Defects Liability Period: 12 months from substantial completion / handover.
A32: Authorised signatory: SABI Engineering & Contracting LLC
A33: TRN: 100XXXXXXXXXXXXX
A34: Signature & Stamp: ____________________________ Date: ____________
